uart/bench.v
`default_nettype none
`timescale 1 ns/1 ns

//==============================================================================

module simple_message
(
  input  logic      _clock,
  input  logic      _reset,
  output logic[7:0] _out,
  output logic      _valid,
  input  logic      _ready
);

  localparam delay_max = 37;

  logic[7:0] text[0:5];
  logic[7:0] delay, delay_;
  logic[7:0] cursor, cursor_;

  initial begin
    $readmemh("ping.hex", text);
    delay  = delay_max;
    cursor = 0;
  end

  always_comb begin
    delay_  = delay;
    cursor_ = cursor;

    if (_reset) begin
      delay_  = delay_max;
      cursor_ = 0;
    end else if (delay_) begin
      delay_ = delay - 1;
    end else if (_valid && _ready) begin
      cursor_ = cursor == 5 ? 0 : cursor + 1;
      if (cursor_ == 0) delay_  = delay_max;
    end
  end

  always @(posedge _clock) begin
    delay  <= delay_;
    cursor <= cursor_;
  end

  assign _out   = _reset ? 0 : delay ? 0 : text[cursor];
  assign _valid = _reset ? 0 : (delay == 0);

endmodule

//==============================================================================

module simple_tx
#(
  parameter clocks_per_bit
)
(
  input logic      _clock,
  input logic      _reset,
  input logic[7:0] _tx_in,
  input logic      _tx_valid,
  output logic     _tx_ready,
  output logic     _tx_out
);

  localparam bits_per_byte = 10; // 1 start + 8 data + 1 stop
  localparam delay_mid = clocks_per_bit > 2 ? (clocks_per_bit / 2) : 0;
  localparam delay_max = clocks_per_bit - 1;
  localparam count_max = bits_per_byte - 1; // 1 start + 8 data + 9 stop to make sure we're really stopped :D

  logic[7:0] tx_delay, tx_delay_;
  logic[7:0] tx_count, tx_count_;
  logic[9:0] tx_shift, tx_shift_;

  initial begin
    tx_delay = delay_max;
    tx_count = count_max;
    tx_shift = 0;
  end

  assign _tx_ready = !_reset && tx_delay == delay_max && tx_count == count_max;
  assign _tx_out   = tx_shift[0];

  wire _tx_bit   = tx_delay == 0 && tx_count > 0 && tx_count < count_max;
  wire _tx_byte  = tx_delay == 0 && tx_count == 1;

  always_comb begin
    if (_reset) begin
      tx_delay_ = delay_max;
      tx_count_ = count_max;
    end else if (tx_delay < delay_max) begin
      tx_delay_ = tx_delay + 1;
      tx_count_ = tx_count;
    end else if (tx_count < count_max) begin
      tx_delay_ = 0;
      tx_count_ = tx_count + 1;
    end else if (_tx_valid && _tx_ready) begin
      tx_delay_ = 0;
      tx_count_ = 0;
    end
  end

  always_comb begin
    if (_reset) begin
      tx_shift_ = 10'b1111111111;
    end else if (_tx_valid && _tx_ready) begin
      tx_shift_ = { 1'b1, _tx_in, 1'b0 };
    end else if (tx_delay_ == 0) begin
      tx_shift_ = { 1'b1, tx_shift[9:1] };
    end else begin
      tx_shift_ = tx_shift;
    end
  end

  always @(posedge _clock) begin
    tx_delay <= tx_delay_;
    tx_count <= tx_count_;
    tx_shift <= tx_shift_;
  end

endmodule

//==============================================================================

module simple_rx
#(
  parameter clocks_per_bit
)
(
  input logic       _clock,
  input logic       _reset,

  input logic       _rx_in,

  output logic[7:0] _rx_out,
  output logic      _rx_valid,
  input logic       _rx_ready
);

  localparam bits_per_byte = 10; // 1 start + 8 data + 1 stop
  localparam delay_mid = clocks_per_bit > 2 ? (clocks_per_bit / 2) : 0;
  localparam delay_max = clocks_per_bit - 1;
  localparam count_max = bits_per_byte - 1; // 1 start + 8 data + 9 stop to make sure we're really stopped :D

  logic[7:0] rx_delay, rx_delay_;
  logic[7:0] rx_count, rx_count_;

  logic[7:0] rx_shift, rx_shift_;
  logic[7:0] rx_data,  rx_data_;

  initial begin
    rx_delay = delay_max;
    rx_count = count_max;
    rx_shift = 0;
    rx_data  = 0;
  end

  assign _rx_ready = !_reset;
  assign _rx_valid = _reset ? 0 : rx_delay == delay_mid && rx_count == count_max - 1;
  assign _rx_out   = rx_data;

  //----------------------------------------

  always_comb begin
    rx_delay_ = rx_delay;
    rx_count_ = rx_count;

    if (_reset) begin
      rx_delay_ = delay_max;
      rx_count_ = count_max;
    end else if (rx_delay < delay_max) begin
      rx_delay_ = rx_delay + 1;
    end else if (rx_count < count_max) begin
      rx_delay_ = 0;
      rx_count_ = rx_count + 1;
    end else if (_rx_in == 0) begin
      rx_delay_ = 0;
      rx_count_ = 0;
    end
  end

  //----------------------------------------

  always_comb begin
    rx_shift_ = rx_shift;

    if (_reset)
      rx_shift_ = 0;
    else if (rx_delay_ == delay_mid)
      rx_shift_ = {_rx_in, rx_shift[7:1]};
  end

  //----------------------------------------

  always_comb begin
    rx_data_  = rx_data;

    if (_reset) begin
      rx_data_  = 0;
    end else if (rx_delay_ == delay_mid && rx_count_ == count_max - 1) begin
      rx_data_  = rx_shift_;
    end
  end

  wire _rx_bit = rx_delay == delay_mid && rx_count > 0 && rx_count < count_max;

  //----------------------------------------

  always @(posedge _clock) begin
    rx_data  <= rx_data_;
    rx_delay <= rx_delay_;
    rx_count <= rx_count_;
    rx_shift <= rx_shift_;
  end

endmodule

//==============================================================================

module bench();

  logic clock;
  logic reset;
  initial clock = 1;
  initial reset = 1;

  initial begin
    clock = 0;
    #45;
    while(1) #5 clock = ~clock;
  end

  initial begin
    $dumpfile ("bench.vcd");
    $dumpvars;

    #95;
    reset = 0;

    #8000 $finish();
  end

  //----------------------------------------------------------------------------

  localparam clocks_per_bit = 9;

  simple_message msg();

  assign msg._clock = clock;
  assign msg._reset = reset;
  assign msg._ready = tx._tx_ready;

  simple_tx #(.clocks_per_bit(clocks_per_bit)) tx();

  assign tx._clock    = clock;
  assign tx._reset    = reset;
  assign tx._tx_in    = msg._out;
  assign tx._tx_valid = msg._valid;

  simple_rx #(.clocks_per_bit(clocks_per_bit)) rx();

  assign rx._clock = clock;
  assign rx._reset = reset;
  assign rx._rx_in = tx._tx_out;

  //----------------------------------------------------------------------------

endmodule

//==============================================================================

uart/bench.vcd
$date
	Mon Jul 29 19:17:16 2024
$end
$version
	Icarus Verilog
$end
$timescale
	1ns
$end
$scope module bench $end
$var parameter 32 ! clocks_per_bit $end
$var reg 1 " clock $end
$var reg 1 # reset $end
$scope module msg $end
$var wire 1 $ _clock $end
$var wire 1 % _ready $end
$var wire 1 & _reset $end
$var wire 1 ' _valid $end
$var wire 8 ( _out [7:0] $end
$var parameter 32 ) delay_max $end
$var reg 8 * cursor [7:0] $end
$var reg 8 + cursor_ [7:0] $end
$var reg 8 , delay [7:0] $end
$var reg 8 - delay_ [7:0] $end
$upscope $end
$scope module rx $end
$var wire 1 . _clock $end
$var wire 1 / _reset $end
$var wire 1 0 _rx_bit $end
$var wire 1 1 _rx_in $end
$var wire 8 2 _rx_out [7:0] $end
$var wire 1 3 _rx_valid $end
$var wire 1 4 _rx_ready $end
$var parameter 32 5 bits_per_byte $end
$var parameter 32 6 clocks_per_bit $end
$var parameter 33 7 count_max $end
$var parameter 33 8 delay_max $end
$var parameter 32 9 delay_mid $end
$var reg 8 : rx_count [7:0] $end
$var reg 8 ; rx_count_ [7:0] $end
$var reg 8 < rx_data [7:0] $end
$var reg 8 = rx_data_ [7:0] $end
$var reg 8 > rx_delay [7:0] $end
$var reg 8 ? rx_delay_ [7:0] $end
$var reg 8 @ rx_shift [7:0] $end
$var reg 8 A rx_shift_ [7:0] $end
$upscope $end
$scope module tx $end
$var wire 1 B _clock $end
$var wire 1 C _reset $end
$var wire 1 D _tx_bit $end
$var wire 1 E _tx_byte $end
$var wire 8 F _tx_in [7:0] $end
$var wire 1 G _tx_ready $end
$var wire 1 H _tx_valid $end
$var wire 1 I _tx_out $end
$var parameter 32 J bits_per_byte $end
$var parameter 32 K clocks_per_bit $end
$var parameter 33 L count_max $end
$var parameter 33 M delay_max $end
$var parameter 32 N delay_mid $end
$var reg 8 O tx_count [7:0] $end
$var reg 8 P tx_count_ [7:0] $end
$var reg 8 Q tx_delay [7:0] $end
$var reg 8 R tx_delay_ [7:0] $end
$var reg 10 S tx_shift [9:0] $end
$var reg 10 T tx_shift_ [9:0] $end
$upscope $end
$upscope $end
$enddefinitions $end
$comment Show the parameter values. $end
$dumpall
b100 N
b1000 M
b1001 L
b1001 K
b1010 J
b100 9
b1000 8
b1001 7
b1001 6
b1010 5
b100101 )
b1001 !
$end
#0
$dumpvars
b1111111111 T
b1111111111 S
b1000 R
b1000 Q
b1001 P
b1001 O
1I
0H
0G
b0 F
0E
0D
1C
0B
b0 A
b0 @
b1000 ?
b1000 >
b0 =
b0 <
b1001 ;
b1001 :
04
03
b0 2
11
00
1/
0.
b100101 -
b100101 ,
b0 +
b0 *
b0 (
0'
1&
0%
0$
1#
0"
$end
#50
1.
1B
1$
1"
#55
0.
0B
0$
0"
#60
1.
1B
1$
1"
#65
0.
0B
0$
0"
#70
1.
1B
1$
1"
#75
0.
0B
0$
0"
#80
1.
1B
1$
1"
#85
0.
0B
0$
0"
#90
1.
1B
1$
1"
#95
1%
1G
b100100 -
0.
0B
0$
0"
14
0/
0C
0&
0#
#100
b100011 -
b100100 ,
1.
1B
1$
1"
#105
0.
0B
0$
0"
#110
b100010 -
b100011 ,
1.
1B
1$
1"
#115
0.
0B
0$
0"
#120
b100001 -
b100010 ,
1.
1B
1$
1"
#125
0.
0B
0$
0"
#130
b100000 -
b100001 ,
1.
1B
1$
1"
#135
0.
0B
0$
0"
#140
b11111 -
b100000 ,
1.
1B
1$
1"
#145
0.
0B
0$
0"
#150
b11110 -
b11111 ,
1.
1B
1$
1"
#155
0.
0B
0$
0"
#160
b11101 -
b11110 ,
1.
1B
1$
1"
#165
0.
0B
0$
0"
#170
b11100 -
b11101 ,
1.
1B
1$
1"
#175
0.
0B
0$
0"
#180
b11011 -
b11100 ,
1.
1B
1$
1"
#185
0.
0B
0$
0"
#190
b11010 -
b11011 ,
1.
1B
1$
1"
#195
0.
0B
0$
0"
#200
b11001 -
b11010 ,
1.
1B
1$
1"
#205
0.
0B
0$
0"
#210
b11000 -
b11001 ,
1.
1B
1$
1"
#215
0.
0B
0$
0"
#220
b10111 -
b11000 ,
1.
1B
1$
1"
#225
0.
0B
0$
0"
#230
b10110 -
b10111 ,
1.
1B
1$
1"
#235
0.
0B
0$
0"
#240
b10101 -
b10110 ,
1.
1B
1$
1"
#245
0.
0B
0$
0"
#250
b10100 -
b10101 ,
1.
1B
1$
1"
#255
0.
0B
0$
0"
#260
b10011 -
b10100 ,
1.
1B
1$
1"
#265
0.
0B
0$
0"
#270
b10010 -
b10011 ,
1.
1B
1$
1"
#275
0.
0B
0$
0"
#280
b10001 -
b10010 ,
1.
1B
1$
1"
#285
0.
0B
0$
0"
#290
b10000 -
b10001 ,
1.
1B
1$
1"
#295
0.
0B
0$
0"
#300
b1111 -
b10000 ,
1.
1B
1$
1"
#305
0.
0B
0$
0"
#310
b1110 -
b1111 ,
1.
1B
1$
1"
#315
0.
0B
0$
0"
#320
b1101 -
b1110 ,
1.
1B
1$
1"
#325
0.
0B
0$
0"
#330
b1100 -
b1101 ,
1.
1B
1$
1"
#335
0.
0B
0$
0"
#340
b1011 -
b1100 ,
1.
1B
1$
1"
#345
0.
0B
0$
0"
#350
b1010 -
b1011 ,
1.
1B
1$
1"
#355
0.
0B
0$
0"
#360
b1001 -
b1010 ,
1.
1B
1$
1"
#365
0.
0B
0$
0"
#370
b1000 -
b1001 ,
1.
1B
1$
1"
#375
0.
0B
0$
0"
#380
b111 -
b1000 ,
1.
1B
1$
1"
#385
0.
0B
0$
0"
#390
b110 -
b111 ,
1.
1B
1$
1"
#395
0.
0B
0$
0"
#400
b101 -
b110 ,
1.
1B
1$
1"
#405
0.
0B
0$
0"
#410
b100 -
b101 ,
1.
1B
1$
1"
#415
0.
0B
0$
0"
#420
b11 -
b100 ,
1.
1B
1$
1"
#425
0.
0B
0$
0"
#430
b10 -
b11 ,
1.
1B
1$
1"
#435
0.
0B
0$
0"
#440
b1 -
b10 ,
1.
1B
1$
1"
#445
0.
0B
0$
0"
#450
b0 -
b1 ,
1.
1B
1$
1"
#455
0.
0B
0$
0"
#460
b1010100000 T
b0 P
b0 R
b1 +
b1010000 F
b1010000 (
1H
1'
b0 ,
1.
1B
1$
1"
#465
0.
0B
0$
0"
#470
b0 ;
b0 ?
0%
0G
b1101001 F
b1101001 (
01
0I
b1 R
b1 +
b1010100000 S
b0 O
b0 Q
b1 *
1.
1B
1$
1"
#475
0.
0B
0$
0"
#480
b1 ?
b10 R
b0 :
b0 >
b1 Q
1.
1B
1$
1"
#485
0.
0B
0$
0"
#490
b10 ?
b11 R
b1 >
b10 Q
1.
1B
1$
1"
#495
0.
0B
0$
0"
#500
b11 ?
b100 R
b10 >
b11 Q
1.
1B
1$
1"
#505
0.
0B
0$
0"
#510
b100 ?
b101 R
b11 >
b100 Q
1.
1B
1$
1"
#515
0.
0B
0$
0"
#520
b101 ?
b110 R
b100 >
b101 Q
1.
1B
1$
1"
#525
0.
0B
0$
0"
#530
b110 ?
b111 R
b101 >
b110 Q
1.
1B
1$
1"
#535
0.
0B
0$
0"
#540
b111 ?
b1000 R
b110 >
b111 Q
1.
1B
1$
1"
#545
0.
0B
0$
0"
#550
b1101010000 T
b1000 ?
b1 P
b0 R
b111 >
b1000 Q
1.
1B
1$
1"
#555
0.
0B
0$
0"
#560
1D
1E
b1 ;
b0 ?
b1 R
b1000 >
b1101010000 S
b1 O
b0 Q
1.
1B
1$
1"
#565
0.
0B
0$
0"
#570
0D
0E
b1 ?
b10 R
b1 :
b0 >
b1 Q
1.
1B
1$
1"
#575
0.
0B
0$
0"
#580
b10 ?
b11 R
b1 >
b10 Q
1.
1B
1$
1"
#585
0.
0B
0$
0"
#590
b11 ?
b100 R
b10 >
b11 Q
1.
1B
1$
1"
#595
0.
0B
0$
0"
#600
b100 ?
b101 R
b11 >
b100 Q
1.
1B
1$
1"
#605
0.
0B
0$
0"
#610
10
b101 ?
b110 R
b100 >
b101 Q
1.
1B
1$
1"
#615
0.
0B
0$
0"
#620
00
b110 ?
b111 R
b101 >
b110 Q
1.
1B
1$
1"
#625
0.
0B
0$
0"
#630
b111 ?
b1000 R
b110 >
b111 Q
1.
1B
1$
1"
#635
0.
0B
0$
0"
#640
b1110101000 T
b1000 ?
b10 P
b0 R
b111 >
b1000 Q
1.
1B
1$
1"
#645
0.
0B
0$
0"
#650
1D
b10 ;
b0 ?
b1 R
b1000 >
b1110101000 S
b10 O
b0 Q
1.
1B
1$
1"
#655
0.
0B
0$
0"
#660
0D
b1 ?
b10 R
b10 :
b0 >
b1 Q
1.
1B
1$
1"
#665
0.
0B
0$
0"
#670
b10 ?
b11 R
b1 >
b10 Q
1.
1B
1$
1"
#675
0.
0B
0$
0"
#680
b11 ?
b100 R
b10 >
b11 Q
1.
1B
1$
1"
#685
0.
0B
0$
0"
#690
b100 ?
b101 R
b11 >
b100 Q
1.
1B
1$
1"
#695
0.
0B
0$
0"
#700
10
b101 ?
b110 R
b100 >
b101 Q
1.
1B
1$
1"
#705
0.
0B
0$
0"
#710
00
b110 ?
b111 R
b101 >
b110 Q
1.
1B
1$
1"
#715
0.
0B
0$
0"
#720
b111 ?
b1000 R
b110 >
b111 Q
1.
1B
1$
1"
#725
0.
0B
0$
0"
#730
b1111010100 T
b1000 ?
b11 P
b0 R
b111 >
b1000 Q
1.
1B
1$
1"
#735
0.
0B
0$
0"
#740
1D
b11 ;
b0 ?
b1 R
b1000 >
b1111010100 S
b11 O
b0 Q
1.
1B
1$
1"
#745
0.
0B
0$
0"
#750
0D
b1 ?
b10 R
b11 :
b0 >
b1 Q
1.
1B
1$
1"
#755
0.
0B
0$
0"
#760
b10 ?
b11 R
b1 >
b10 Q
1.
1B
1$
1"
#765
0.
0B
0$
0"
#770
b11 ?
b100 R
b10 >
b11 Q
1.
1B
1$
1"
#775
0.
0B
0$
0"
#780
b100 ?
b101 R
b11 >
b100 Q
1.
1B
1$
1"
#785
0.
0B
0$
0"
#790
10
b101 ?
b110 R
b100 >
b101 Q
1.
1B
1$
1"
#795
0.
0B
0$
0"
#800
00
b110 ?
b111 R
b101 >
b110 Q
1.
1B
1$
1"
#805
0.
0B
0$
0"
#810
b111 ?
b1000 R
b110 >
b111 Q
1.
1B
1$
1"
#815
0.
0B
0$
0"
#820
b1111101010 T
b1000 ?
b100 P
b0 R
b111 >
b1000 Q
1.
1B
1$
1"
#825
0.
0B
0$
0"
#830
1D
b100 ;
b0 ?
b1 R
b1000 >
b1111101010 S
b100 O
b0 Q
1.
1B
1$
1"
#835
0.
0B
0$
0"
#840
0D
b1 ?
b10 R
b100 :
b0 >
b1 Q
1.
1B
1$
1"
#845
0.
0B
0$
0"
#850
b10 ?
b11 R
b1 >
b10 Q
1.
1B
1$
1"
#855
0.
0B
0$
0"
#860
b11 ?
b100 R
b10 >
b11 Q
1.
1B
1$
1"
#865
0.
0B
0$
0"
#870
b100 ?
b101 R
b11 >
b100 Q
1.
1B
1$
1"
#875
0.
0B
0$
0"
#880
10
b101 ?
b110 R
b100 >
b101 Q
1.
1B
1$
1"
#885
0.
0B
0$
0"
#890
00
b110 ?
b111 R
b101 >
b110 Q
1.
1B
1$
1"
#895
0.
0B
0$
0"
#900
b111 ?
b1000 R
b110 >
b111 Q
1.
1B
1$
1"
#905
0.
0B
0$
0"
#910
b1111110101 T
b1000 ?
b101 P
b0 R
b111 >
b1000 Q
1.
1B
1$
1"
#915
0.
0B
0$
0"
#920
1D
b101 ;
b0 ?
11
1I
b1 R
b1000 >
b1111110101 S
b101 O
b0 Q
1.
1B
1$
1"
#925
0.
0B
0$
0"
#930
0D
b1 ?
b10 R
b101 :
b0 >
b1 Q
1.
1B
1$
1"
#935
0.
0B
0$
0"
#940
b10 ?
b11 R
b1 >
b10 Q
1.
1B
1$
1"
#945
0.
0B
0$
0"
#950
b11 ?
b100 R
b10 >
b11 Q
1.
1B
1$
1"
#955
0.
0B
0$
0"
#960
b10000000 A
b100 ?
b101 R
b11 >
b100 Q
1.
1B
1$
1"
#965
0.
0B
0$
0"
#970
10
b101 ?
b110 R
b10000000 @
b100 >
b101 Q
1.
1B
1$
1"
#975
0.
0B
0$
0"
#980
00
b110 ?
b111 R
b101 >
b110 Q
1.
1B
1$
1"
#985
0.
0B
0$
0"
#990
b111 ?
b1000 R
b110 >
b111 Q
1.
1B
1$
1"
#995
0.
0B
0$
0"
#1000
b1111111010 T
b1000 ?
b110 P
b0 R
b111 >
b1000 Q
1.
1B
1$
1"
#1005
0.
0B
0$
0"
#1010
1D
b110 ;
b0 ?
01
0I
b1 R
b1000 >
b1111111010 S
b110 O
b0 Q
1.
1B
1$
1"
#1015
0.
0B
0$
0"
#1020
0D
b1 ?
b10 R
b110 :
b0 >
b1 Q
1.
1B
1$
1"
#1025
0.
0B
0$
0"
#1030
b10 ?
b11 R
b1 >
b10 Q
1.
1B
1$
1"
#1035
0.
0B
0$
0"
#1040
b11 ?
b100 R
b10 >
b11 Q
1.
1B
1$
1"
#1045
0.
0B
0$
0"
#1050
b1000000 A
b100 ?
b101 R
b11 >
b100 Q
1.
1B
1$
1"
#1055
0.
0B
0$
0"
#1060
10
b101 ?
b110 R
b1000000 @
b100 >
b101 Q
1.
1B
1$
1"
#1065
0.
0B
0$
0"
#1070
00
b110 ?
b111 R
b101 >
b110 Q
1.
1B
1$
1"
#1075
0.
0B
0$
0"
#1080
b111 ?
b1000 R
b110 >
b111 Q
1.
1B
1$
1"
#1085
0.
0B
0$
0"
#1090
b1111111101 T
b1000 ?
b111 P
b0 R
b111 >
b1000 Q
1.
1B
1$
1"
#1095
0.
0B
0$
0"
#1100
1D
b111 ;
b0 ?
11
1I
b1 R
b1000 >
b1111111101 S
b111 O
b0 Q
1.
1B
1$
1"
#1105
0.
0B
0$
0"
#1110
0D
b1 ?
b10 R
b111 :
b0 >
b1 Q
1.
1B
1$
1"
#1115
0.
0B
0$
0"
#1120
b10 ?
b11 R
b1 >
b10 Q
1.
1B
1$
1"
#1125
0.
0B
0$
0"
#1130
b11 ?
b100 R
b10 >
b11 Q
1.
1B
1$
1"
#1135
0.
0B
0$
0"
#1140
b10100000 A
b100 ?
b101 R
b11 >
b100 Q
1.
1B
1$
1"
#1145
0.
0B
0$
0"
#1150
10
b101 ?
b110 R
b10100000 @
b100 >
b101 Q
1.
1B
1$
1"
#1155
0.
0B
0$
0"
#1160
00
b110 ?
b111 R
b101 >
b110 Q
1.
1B
1$
1"
#1165
0.
0B
0$
0"
#1170
b111 ?
b1000 R
b110 >
b111 Q
1.
1B
1$
1"
#1175
0.
0B
0$
0"
#1180
b1111111110 T
b1000 ?
b1000 P
b0 R
b111 >
b1000 Q
1.
1B
1$
1"
#1185
0.
0B
0$
0"
#1190
1D
b1000 ;
b0 ?
01
0I
b1 R
b1000 >
b1111111110 S
b1000 O
b0 Q
1.
1B
1$
1"
#1195
0.
0B
0$
0"
#1200
0D
b1 ?
b10 R
b1000 :
b0 >
b1 Q
1.
1B
1$
1"
#1205
0.
0B
0$
0"
#1210
b10 ?
b11 R
b1 >
b10 Q
1.
1B
1$
1"
#1215
0.
0B
0$
0"
#1220
b11 ?
b100 R
b10 >
b11 Q
1.
1B
1$
1"
#1225
0.
0B
0$
0"
#1230
b1010000 =
b1010000 A
b100 ?
b101 R
b11 >
b100 Q
1.
1B
1$
1"
#1235
0.
0B
0$
0"
#1240
13
10
b101 ?
b110 R
b1010000 @
b100 >
b1010000 2
b1010000 <
b101 Q
1.
1B
1$
1"
#1245
0.
0B
0$
0"
#1250
03
00
b110 ?
b111 R
b101 >
b110 Q
1.
1B
1$
1"
#1255
0.
0B
0$
0"
#1260
b111 ?
b1000 R
b110 >
b111 Q
1.
1B
1$
1"
#1265
0.
0B
0$
0"
#1270
b1111111111 T
b1000 ?
b1001 P
b0 R
b111 >
b1000 Q
1.
1B
1$
1"
#1275
0.
0B
0$
0"
#1280
b1001 ;
b0 ?
11
1I
b1 R
b1000 >
b1111111111 S
b1001 O
b0 Q
1.
1B
1$
1"
#1285
0.
0B
0$
0"
#1290
b1 ?
b10 R
b1001 :
b0 >
b1 Q
1.
1B
1$
1"
#1295
0.
0B
0$
0"
#1300
b10 ?
b11 R
b1 >
b10 Q
1.
1B
1$
1"
#1305
0.
0B
0$
0"
#1310
b11 ?
b100 R
b10 >
b11 Q
1.
1B
1$
1"
#1315
0.
0B
0$
0"
#1320
b10101000 A
b100 ?
b101 R
b11 >
b100 Q
1.
1B
1$
1"
#1325
0.
0B
0$
0"
#1330
b101 ?
b110 R
b10101000 @
b100 >
b101 Q
1.
1B
1$
1"
#1335
0.
0B
0$
0"
#1340
b110 ?
b111 R
b101 >
b110 Q
1.
1B
1$
1"
#1345
0.
0B
0$
0"
#1350
b111 ?
b1000 R
b110 >
b111 Q
1.
1B
1$
1"
#1355
0.
0B
0$
0"
#1360
b1011010010 T
b0 P
b0 R
b10 +
1%
1G
b1000 ?
b111 >
b1000 Q
1.
1B
1$
1"
#1365
0.
0B
0$
0"
#1370
0%
0G
b1101110 F
b1101110 (
b0 ;
b0 ?
01
0I
b1 R
b10 +
b1000 >
b1011010010 S
b0 O
b0 Q
b10 *
1.
1B
1$
1"
#1375
0.
0B
0$
0"
#1380
b1 ?
b10 R
b0 :
b0 >
b1 Q
1.
1B
1$
1"
#1385
0.
0B
0$
0"
#1390
b10 ?
b11 R
b1 >
b10 Q
1.
1B
1$
1"
#1395
0.
0B
0$
0"
#1400
b11 ?
b100 R
b10 >
b11 Q
1.
1B
1$
1"
#1405
0.
0B
0$
0"
#1410
b1010100 A
b100 ?
b101 R
b11 >
b100 Q
1.
1B
1$
1"
#1415
0.
0B
0$
0"
#1420
b101 ?
b110 R
b1010100 @
b100 >
b101 Q
1.
1B
1$
1"
#1425
0.
0B
0$
0"
#1430
b110 ?
b111 R
b101 >
b110 Q
1.
1B
1$
1"
#1435
0.
0B
0$
0"
#1440
b111 ?
b1000 R
b110 >
b111 Q
1.
1B
1$
1"
#1445
0.
0B
0$
0"
#1450
b1101101001 T
b1000 ?
b1 P
b0 R
b111 >
b1000 Q
1.
1B
1$
1"
#1455
0.
0B
0$
0"
#1460
1D
1E
b1 ;
b0 ?
11
1I
b1 R
b1000 >
b1101101001 S
b1 O
b0 Q
1.
1B
1$
1"
#1465
0.
0B
0$
0"
#1470
0D
0E
b1 ?
b10 R
b1 :
b0 >
b1 Q
1.
1B
1$
1"
#1475
0.
0B
0$
0"
#1480
b10 ?
b11 R
b1 >
b10 Q
1.
1B
1$
1"
#1485
0.
0B
0$
0"
#1490
b11 ?
b100 R
b10 >
b11 Q
1.
1B
1$
1"
#1495
0.
0B
0$
0"
#1500
b10101010 A
b100 ?
b101 R
b11 >
b100 Q
1.
1B
1$
1"
#1505
0.
0B
0$
0"
#1510
10
b101 ?
b110 R
b10101010 @
b100 >
b101 Q
1.
1B
1$
1"
#1515
0.
0B
0$
0"
#1520
00
b110 ?
b111 R
b101 >
b110 Q
1.
1B
1$
1"
#1525
0.
0B
0$
0"
#1530
b111 ?
b1000 R
b110 >
b111 Q
1.
1B
1$
1"
#1535
0.
0B
0$
0"
#1540
b1110110100 T
b1000 ?
b10 P
b0 R
b111 >
b1000 Q
1.
1B
1$
1"
#1545
0.
0B
0$
0"
#1550
1D
b10 ;
b0 ?
01
0I
b1 R
b1000 >
b1110110100 S
b10 O
b0 Q
1.
1B
1$
1"
#1555
0.
0B
0$
0"
#1560
0D
b1 ?
b10 R
b10 :
b0 >
b1 Q
1.
1B
1$
1"
#1565
0.
0B
0$
0"
#1570
b10 ?
b11 R
b1 >
b10 Q
1.
1B
1$
1"
#1575
0.
0B
0$
0"
#1580
b11 ?
b100 R
b10 >
b11 Q
1.
1B
1$
1"
#1585
0.
0B
0$
0"
#1590
b1010101 A
b100 ?
b101 R
b11 >
b100 Q
1.
1B
1$
1"
#1595
0.
0B
0$
0"
#1600
10
b101 ?
b110 R
b1010101 @
b100 >
b101 Q
1.
1B
1$
1"
#1605
0.
0B
0$
0"
#1610
00
b110 ?
b111 R
b101 >
b110 Q
1.
1B
1$
1"
#1615
0.
0B
0$
0"
#1620
b111 ?
b1000 R
b110 >
b111 Q
1.
1B
1$
1"
#1625
0.
0B
0$
0"
#1630
b1111011010 T
b1000 ?
b11 P
b0 R
b111 >
b1000 Q
1.
1B
1$
1"
#1635
0.
0B
0$
0"
#1640
1D
b11 ;
b0 ?
b1 R
b1000 >
b1111011010 S
b11 O
b0 Q
1.
1B
1$
1"
#1645
0.
0B
0$
0"
#1650
0D
b1 ?
b10 R
b11 :
b0 >
b1 Q
1.
1B
1$
1"
#1655
0.
0B
0$
0"
#1660
b10 ?
b11 R
b1 >
b10 Q
1.
1B
1$
1"
#1665
0.
0B
0$
0"
#1670
b11 ?
b100 R
b10 >
b11 Q
1.
1B
1$
1"
#1675
0.
0B
0$
0"
#1680
b101010 A
b100 ?
b101 R
b11 >
b100 Q
1.
1B
1$
1"
#1685
0.
0B
0$
0"
#1690
10
b101 ?
b110 R
b101010 @
b100 >
b101 Q
1.
1B
1$
1"
#1695
0.
0B
0$
0"
#1700
00
b110 ?
b111 R
b101 >
b110 Q
1.
1B
1$
1"
#1705
0.
0B
0$
0"
#1710
b111 ?
b1000 R
b110 >
b111 Q
1.
1B
1$
1"
#1715
0.
0B
0$
0"
#1720
b1111101101 T
b1000 ?
b100 P
b0 R
b111 >
b1000 Q
1.
1B
1$
1"
#1725
0.
0B
0$
0"
#1730
1D
b100 ;
b0 ?
11
1I
b1 R
b1000 >
b1111101101 S
b100 O
b0 Q
1.
1B
1$
1"
#1735
0.
0B
0$
0"
#1740
0D
b1 ?
b10 R
b100 :
b0 >
b1 Q
1.
1B
1$
1"
#1745
0.
0B
0$
0"
#1750
b10 ?
b11 R
b1 >
b10 Q
1.
1B
1$
1"
#1755
0.
0B
0$
0"
#1760
b11 ?
b100 R
b10 >
b11 Q
1.
1B
1$
1"
#1765
0.
0B
0$
0"
#1770
b10010101 A
b100 ?
b101 R
b11 >
b100 Q
1.
1B
1$
1"
#1775
0.
0B
0$
0"
#1780
10
b101 ?
b110 R
b10010101 @
b100 >
b101 Q
1.
1B
1$
1"
#1785
0.
0B
0$
0"
#1790
00
b110 ?
b111 R
b101 >
b110 Q
1.
1B
1$
1"
#1795
0.
0B
0$
0"
#1800
b111 ?
b1000 R
b110 >
b111 Q
1.
1B
1$
1"
#1805
0.
0B
0$
0"
#1810
b1111110110 T
b1000 ?
b101 P
b0 R
b111 >
b1000 Q
1.
1B
1$
1"
#1815
0.
0B
0$
0"
#1820
1D
b101 ;
b0 ?
01
0I
b1 R
b1000 >
b1111110110 S
b101 O
b0 Q
1.
1B
1$
1"
#1825
0.
0B
0$
0"
#1830
0D
b1 ?
b10 R
b101 :
b0 >
b1 Q
1.
1B
1$
1"
#1835
0.
0B
0$
0"
#1840
b10 ?
b11 R
b1 >
b10 Q
1.
1B
1$
1"
#1845
0.
0B
0$
0"
#1850
b11 ?
b100 R
b10 >
b11 Q
1.
1B
1$
1"
#1855
0.
0B
0$
0"
#1860
b1001010 A
b100 ?
b101 R
b11 >
b100 Q
1.
1B
1$
1"
#1865
0.
0B
0$
0"
#1870
10
b101 ?
b110 R
b1001010 @
b100 >
b101 Q
1.
1B
1$
1"
#1875
0.
0B
0$
0"
#1880
00
b110 ?
b111 R
b101 >
b110 Q
1.
1B
1$
1"
#1885
0.
0B
0$
0"
#1890
b111 ?
b1000 R
b110 >
b111 Q
1.
1B
1$
1"
#1895
0.
0B
0$
0"
#1900
b1111111011 T
b1000 ?
b110 P
b0 R
b111 >
b1000 Q
1.
1B
1$
1"
#1905
0.
0B
0$
0"
#1910
1D
b110 ;
b0 ?
11
1I
b1 R
b1000 >
b1111111011 S
b110 O
b0 Q
1.
1B
1$
1"
#1915
0.
0B
0$
0"
#1920
0D
b1 ?
b10 R
b110 :
b0 >
b1 Q
1.
1B
1$
1"
#1925
0.
0B
0$
0"
#1930
b10 ?
b11 R
b1 >
b10 Q
1.
1B
1$
1"
