uart/bench.v
`default_nettype none
`timescale 1 ns/1 ns

//==============================================================================

module simple_message
(
  input  logic      _clock,
  input  logic      _reset,
  output logic[7:0] _out,
  output logic      _valid,
  input  logic      _ready
);

  localparam delay_max = 20;

  logic[7:0] text[0:5];
  logic[7:0] delay, delay_;
  logic[7:0] cursor, cursor_;

  initial begin
    $readmemh("ping.hex", text);
    delay  = delay_max;
    cursor = 0;
  end

  always_comb begin
    if (_reset) begin
      delay_  = delay_max;
      cursor_ = 0;
    end else if (delay) begin
      delay_  = delay - 1;
      cursor_ = cursor;
    end else if (_valid && _ready) begin
      delay_  = cursor == 5 ? delay_max - 1 : delay;
      cursor_ = cursor == 5 ? 0 : cursor + 1;
    end else begin
      delay_  = delay;
      cursor_ = cursor;
    end
  end

  always @(posedge _clock) begin
    delay  <= delay_;
    cursor <= cursor_;
  end

  assign _out   = _reset ? 0 : delay ? 0 : text[cursor];
  assign _valid = _reset ? 0 : (delay == 0);

endmodule

//==============================================================================

module simple_tx
#(
  parameter clocks_per_bit
)
(
  input logic      _clock,
  input logic      _reset,

  input logic[7:0] _tx_in,
  input logic      _source_valid,

  output logic     _sink_ready,
  output logic     _tx_out
);

  localparam bits_per_byte = 10; // 1 start + 8 data + 1 stop
  localparam delay_mid = clocks_per_bit / 2;
  localparam delay_max = clocks_per_bit - 1;
  localparam count_max = bits_per_byte - 1; // 1 start + 8 data + 9 stop to make sure we're really stopped :D

  logic[7:0] tx_delay, tx_delay_;
  logic[7:0] tx_count, tx_count_;
  logic[9:0] tx_shift, tx_shift_;

  initial begin
    tx_delay = delay_max;
    tx_count = count_max;
    tx_shift = 10'b1111111111;
  end

  assign _sink_ready = !_reset && tx_delay == delay_max && tx_count == count_max;
  assign _tx_out   = tx_shift[0];

  wire _tx_bit   = tx_delay == 0 && tx_count > 0 && tx_count < count_max;
  wire _tx_byte  = tx_delay == 0 && tx_count == 1;

  always_comb begin
    if (_reset) begin
      tx_delay_ = delay_max;
      tx_count_ = count_max;
    end else if (tx_delay < delay_max) begin
      tx_delay_ = tx_delay + 1;
      tx_count_ = tx_count;
    end else if (tx_count < count_max) begin
      tx_delay_ = 0;
      tx_count_ = tx_count + 1;
    end else if (_source_valid && _sink_ready) begin
      tx_delay_ = 0;
      tx_count_ = 0;
    end
  end

  always_comb begin
    if (_reset) begin
      tx_shift_ = 10'b1111111111;
    end else if (_source_valid && _sink_ready) begin
      tx_shift_ = { 1'b1, _tx_in, 1'b0 };
    end else if (tx_delay_ == 0) begin
      tx_shift_ = { 1'b1, tx_shift[9:1] };
    end else begin
      tx_shift_ = tx_shift;
    end
  end

  always @(posedge _clock) begin
    tx_delay <= tx_delay_;
    tx_count <= tx_count_;
    tx_shift <= tx_shift_;
  end

endmodule

//==============================================================================

module simple_rx
#(
  parameter clocks_per_bit
)
(
  input logic       _clock,
  input logic       _reset,

  input logic       _in,

  output logic[7:0] _out,
  output logic      _source_valid,
  input  logic      _sink_ready
);

  localparam bits_per_byte = 10; // 1 start + 8 data + 1 stop
  localparam delay_mid = clocks_per_bit / 2;
  localparam delay_max = clocks_per_bit - 1;
  localparam count_max = bits_per_byte - 1; // 1 start + 8 data + 9 stop to make sure we're really stopped :D

  logic[7:0] rx_delay, rx_delay_;
  logic[7:0] rx_count, rx_count_;

  logic[7:0] rx_shift, rx_shift_;
  logic[7:0] rx_data,  rx_data_;
  logic[7:0] rx_valid, rx_valid_;

  logic[31:0] rx_sum, rx_sum_;

  initial begin
    rx_delay = delay_max;
    rx_count = count_max;
    rx_shift = 0;
    rx_data  = 0;
    rx_sum   = 0;
  end

  assign _source_valid = _reset ? 0 : rx_delay == delay_mid && rx_count == count_max - 1;
  assign _out   = rx_data;

  //----------------------------------------

  always_comb begin
    if (_reset) begin
      rx_delay_ = delay_max;
      rx_count_ = count_max;
    end else if (rx_delay < delay_max) begin
      rx_delay_ = rx_delay + 1;
    end else if (rx_count < count_max) begin
      rx_delay_ = 0;
      rx_count_ = rx_count + 1;
    end else if (_in == 0) begin
      rx_delay_ = 0;
      rx_count_ = 0;
    end else begin
      rx_delay_ = rx_delay;
      rx_count_ = rx_count;
    end
  end

  //----------------------------------------

  always_comb begin
    if (_reset) begin
      rx_data_  = 0;
      rx_valid_ = 0;
    end else if (rx_delay_ == delay_mid && rx_count_ == count_max - 1) begin
      rx_data_  = rx_shift_;
      rx_sum_   = rx_sum + rx_shift_;
      rx_valid_ = 1;
    end else begin
      rx_data_  = rx_data;
      rx_valid_ = rx_valid;
    end
  end

  //----------------------------------------

  always_comb begin
    if (_reset) begin
      rx_shift_ = 0;
    end else if (rx_delay_ == delay_mid) begin
      rx_shift_ = {_in, rx_shift[7:1]};
    end else begin
      rx_shift_ = rx_shift;
    end
  end

  //----------------------------------------

  always @(posedge _clock) begin
    rx_data  <= rx_data_;
    rx_delay <= rx_delay_;
    rx_count <= rx_count_;
    rx_shift <= rx_shift_;
    rx_sum   <= rx_sum_;
  end

  wire _rx_bit = rx_delay == delay_mid && rx_count > 0 && rx_count < count_max;

endmodule

//==============================================================================

module byte_sink
(
  input logic      _clock,
  input logic      _reset,
  input logic[7:0] _data,
  input logic      _source_valid,
  output logic     _sink_ready
);

  always_comb begin
    _sink_ready = !_reset;
  end

endmodule

//==============================================================================

module bench();

  logic clock = 1;
  logic reset = 1;

  always #5 clock = ~clock;

  initial begin
    $dumpfile ("bench.vcd");
    $dumpvars;

    #95;
    reset = 0;

    #8000 $finish();
  end

  //----------------------------------------------------------------------------

  localparam clocks_per_bit = 1;

  simple_message msg();

  assign msg._clock = clock;
  assign msg._reset = reset;
  assign msg._ready = tx._sink_ready;

  simple_tx #(.clocks_per_bit(clocks_per_bit)) tx();

  assign tx._clock    = clock;
  assign tx._reset    = reset;
  assign tx._tx_in    = msg._out;
  assign tx._source_valid = msg._valid;

  simple_rx #(.clocks_per_bit(clocks_per_bit)) rx();

  assign rx._clock = clock;
  assign rx._reset = reset;
  assign rx._in = tx._tx_out;
  assign rx._sink_ready = sink._sink_ready;

  byte_sink sink();
  assign sink._clock = clock;
  assign sink._reset = reset;
  assign sink._data  = rx._out;
  assign sink._source_valid = rx._source_valid;

  //----------------------------------------------------------------------------

endmodule

//==============================================================================

uart/bench.vcd
$date
	Tue Jul 30 21:14:38 2024
$end
$version
	Icarus Verilog
$end
$timescale
	1ns
$end
$scope module bench $end
$var parameter 32 ! clocks_per_bit $end
$var reg 1 " clock $end
$var reg 1 # reset $end
$scope module msg $end
$var wire 1 $ _clock $end
$var wire 1 % _ready $end
$var wire 1 & _reset $end
$var wire 1 ' _valid $end
$var wire 8 ( _out [7:0] $end
$var parameter 32 ) delay_max $end
$var reg 8 * cursor [7:0] $end
$var reg 8 + cursor_ [7:0] $end
$var reg 8 , delay [7:0] $end
$var reg 8 - delay_ [7:0] $end
$upscope $end
$scope module rx $end
$var wire 1 . _clock $end
$var wire 1 / _in $end
$var wire 1 0 _reset $end
$var wire 1 1 _rx_bit $end
$var wire 1 2 _sink_ready $end
$var wire 1 3 _source_valid $end
$var wire 8 4 _out [7:0] $end
$var parameter 32 5 bits_per_byte $end
$var parameter 32 6 clocks_per_bit $end
$var parameter 33 7 count_max $end
$var parameter 33 8 delay_max $end
$var parameter 32 9 delay_mid $end
$var reg 8 : rx_count [7:0] $end
$var reg 8 ; rx_count_ [7:0] $end
$var reg 8 < rx_data [7:0] $end
$var reg 8 = rx_data_ [7:0] $end
$var reg 8 > rx_delay [7:0] $end
$var reg 8 ? rx_delay_ [7:0] $end
$var reg 8 @ rx_shift [7:0] $end
$var reg 8 A rx_shift_ [7:0] $end
$var reg 32 B rx_sum [31:0] $end
$var reg 32 C rx_sum_ [31:0] $end
$var reg 8 D rx_valid [7:0] $end
$var reg 8 E rx_valid_ [7:0] $end
$upscope $end
$scope module sink $end
$var wire 1 F _clock $end
$var wire 8 G _data [7:0] $end
$var wire 1 H _reset $end
$var wire 1 I _source_valid $end
$var reg 1 J _sink_ready $end
$upscope $end
$scope module tx $end
$var wire 1 K _clock $end
$var wire 1 L _reset $end
$var wire 1 M _sink_ready $end
$var wire 1 N _source_valid $end
$var wire 1 O _tx_bit $end
$var wire 1 P _tx_byte $end
$var wire 8 Q _tx_in [7:0] $end
$var wire 1 R _tx_out $end
$var parameter 32 S bits_per_byte $end
$var parameter 32 T clocks_per_bit $end
$var parameter 33 U count_max $end
$var parameter 33 V delay_max $end
$var parameter 32 W delay_mid $end
$var reg 8 X tx_count [7:0] $end
$var reg 8 Y tx_count_ [7:0] $end
$var reg 8 Z tx_delay [7:0] $end
$var reg 8 [ tx_delay_ [7:0] $end
$var reg 10 \ tx_shift [9:0] $end
$var reg 10 ] tx_shift_ [9:0] $end
$upscope $end
$upscope $end
$enddefinitions $end
$comment Show the parameter values. $end
$dumpall
b0 W
b0 V
b1001 U
b1 T
b1010 S
b0 9
b0 8
b1001 7
b1 6
b1010 5
b10100 )
b1 !
$end
#0
$dumpvars
b1111111111 ]
b1111111111 \
b0 [
b0 Z
b1001 Y
b1001 X
1R
b0 Q
0P
0O
0N
0M
1L
1K
0J
0I
1H
b0 G
1F
b0 E
bx D
bx C
b0 B
b0 A
b0 @
b0 ?
b0 >
b0 =
b0 <
b1001 ;
b1001 :
b0 4
03
02
01
10
1/
1.
b10100 -
b10100 ,
b0 +
b0 *
b0 (
0'
1&
0%
1$
1#
1"
$end
#5
0F
0.
0K
0$
0"
#10
bx B
1F
1.
1K
1$
1"
#15
0F
0.
0K
0$
0"
#20
1F
1.
1K
1$
1"
#25
0F
0.
0K
0$
0"
#30
1F
1.
1K
1$
1"
#35
0F
0.
0K
0$
0"
#40
1F
1.
1K
1$
1"
#45
0F
0.
0K
0$
0"
#50
1F
1.
1K
1$
1"
#55
0F
0.
0K
0$
0"
#60
1F
1.
1K
1$
1"
#65
0F
0.
0K
0$
0"
#70
1F
1.
1K
1$
1"
#75
0F
0.
0K
0$
0"
#80
1F
1.
1K
1$
1"
#85
0F
0.
0K
0$
0"
#90
1F
1.
1K
1$
1"
#95
1%
1M
12
1J
b10000000 A
bx E
b10011 -
0F
0.
0K
0$
0"
0H
00
0L
0&
0#
#100
b11000000 A
b10010 -
b10000000 @
b10011 ,
1F
1.
1K
1$
1"
#105
0F
0.
0K
0$
0"
#110
b11100000 A
b10001 -
b11000000 @
b10010 ,
1F
1.
1K
1$
1"
#115
0F
0.
0K
0$
0"
#120
b11110000 A
b10000 -
b11100000 @
b10001 ,
1F
1.
1K
1$
1"
#125
0F
0.
0K
0$
0"
#130
b11111000 A
b1111 -
b11110000 @
b10000 ,
1F
1.
1K
1$
1"
#135
0F
0.
0K
0$
0"
#140
b11111100 A
b1110 -
b11111000 @
b1111 ,
1F
1.
1K
1$
1"
#145
0F
0.
0K
0$
0"
#150
b11111110 A
b1101 -
b11111100 @
b1110 ,
1F
1.
1K
1$
1"
#155
0F
0.
0K
0$
0"
#160
b11111111 A
b1100 -
b11111110 @
b1101 ,
1F
1.
1K
1$
1"
#165
0F
0.
0K
0$
0"
#170
b1011 -
b11111111 @
b1100 ,
1F
1.
1K
1$
1"
#175
0F
0.
0K
0$
0"
#180
b1010 -
b1011 ,
1F
1.
1K
1$
1"
#185
0F
0.
0K
0$
0"
#190
b1001 -
b1010 ,
1F
1.
1K
1$
1"
#195
0F
0.
0K
0$
0"
#200
b1000 -
b1001 ,
1F
1.
1K
1$
1"
#205
0F
0.
0K
0$
0"
#210
b111 -
b1000 ,
1F
1.
1K
1$
1"
#215
0F
0.
0K
0$
0"
#220
b110 -
b111 ,
1F
1.
1K
1$
1"
#225
0F
0.
0K
0$
0"
#230
b101 -
b110 ,
1F
1.
1K
1$
1"
#235
0F
0.
0K
0$
0"
#240
b100 -
b101 ,
1F
1.
1K
1$
1"
#245
0F
0.
0K
0$
0"
#250
b11 -
b100 ,
1F
1.
1K
1$
1"
#255
0F
0.
0K
0$
0"
#260
b10 -
b11 ,
1F
1.
1K
1$
1"
#265
0F
0.
0K
0$
0"
#270
b1 -
b10 ,
1F
1.
1K
1$
1"
#275
0F
0.
0K
0$
0"
#280
b0 -
b1 ,
1F
1.
1K
1$
1"
#285
0F
0.
0K
0$
0"
#290
b1010100000 ]
b0 Y
b1 +
b1010000 Q
b1010000 (
1N
1'
b0 ,
1F
1.
1K
1$
1"
#295
0F
0.
0K
0$
0"
#300
b1101010000 ]
b1111111 A
b0 ;
0%
0M
0O
b1101001 Q
b1101001 (
0/
0R
b1 Y
b1 +
b1010100000 \
b0 X
b1 *
1F
1.
1K
1$
1"
#305
0F
0.
0K
0$
0"
#310
1O
01
1P
b111111 A
b1 ;
b1110101000 ]
b10 Y
b1111111 @
b0 :
b1101010000 \
b1 X
1F
1.
1K
1$
1"
#315
0F
0.
0K
0$
0"
#320
11
0P
b11111 A
b10 ;
b1111010100 ]
b11 Y
b111111 @
b1 :
b1110101000 \
b10 X
1F
1.
1K
1$
1"
#325
0F
0.
0K
0$
0"
#330
b1111 A
b11 ;
b1111101010 ]
b100 Y
b11111 @
b10 :
b1111010100 \
b11 X
1F
1.
1K
1$
1"
#335
0F
0.
0K
0$
0"
#340
b111 A
b100 ;
b1111110101 ]
b101 Y
b1111 @
b11 :
b1111101010 \
b100 X
1F
1.
1K
1$
1"
#345
0F
0.
0K
0$
0"
#350
b10000011 A
b101 ;
b1111111010 ]
1/
1R
b110 Y
b111 @
b100 :
b1111110101 \
b101 X
1F
1.
1K
1$
1"
#355
0F
0.
0K
0$
0"
#360
b1000001 A
b110 ;
b1111111101 ]
0/
0R
b111 Y
b10000011 @
b101 :
b1111111010 \
b110 X
1F
1.
1K
1$
1"
#365
0F
0.
0K
0$
0"
#370
b10100000 A
b111 ;
b1111111110 ]
1/
1R
b1000 Y
b1000001 @
b110 :
b1111111101 \
b111 X
1F
1.
1K
1$
1"
#375
0F
0.
0K
0$
0"
#380
b1 E
b1010000 =
b1010000 A
b1000 ;
b1111111111 ]
0/
0R
b1001 Y
b10100000 @
b111 :
b1111111110 \
b1000 X
1F
1.
1K
1$
1"
#385
0F
0.
0K
0$
0"
#390
1I
13
b1011010010 ]
b0 Y
b10 +
bx E
1%
1M
0O
b10101000 A
b1001 ;
1/
1R
b1010000 @
b1000 :
b1010000 G
b1010000 4
b1010000 <
b1111111111 \
b1001 X
1F
1.
1K
1$
1"
#395
0F
0.
0K
0$
0"
#400
0I
03
b1101101001 ]
01
0%
0M
0O
b1101110 Q
b1101110 (
b1010100 A
b0 ;
0/
0R
b1 Y
b10 +
b10101000 @
b1001 :
b1011010010 \
b0 X
b10 *
1F
1.
1K
1$
1"
#405
0F
0.
0K
0$
0"
#410
1O
01
1P
b10101010 A
b1 ;
b1110110100 ]
1/
1R
b10 Y
b1010100 @
b0 :
b1101101001 \
b1 X
1F
1.
1K
1$
1"
#415
0F
0.
0K
0$
0"
#420
11
0P
b1010101 A
b10 ;
b1111011010 ]
0/
0R
b11 Y
b10101010 @
b1 :
b1110110100 \
b10 X
1F
1.
1K
1$
1"
#425
0F
0.
0K
0$
0"
#430
b101010 A
b11 ;
b1111101101 ]
b100 Y
b1010101 @
b10 :
b1111011010 \
b11 X
1F
1.
1K
1$
1"
#435
0F
0.
0K
0$
0"
#440
b10010101 A
b100 ;
b1111110110 ]
1/
1R
b101 Y
b101010 @
b11 :
b1111101101 \
b100 X
1F
1.
1K
1$
1"
#445
0F
0.
0K
0$
0"
#450
b1001010 A
b101 ;
b1111111011 ]
0/
0R
b110 Y
b10010101 @
b100 :
b1111110110 \
b101 X
1F
1.
1K
1$
1"
#455
0F
0.
0K
0$
0"
#460
b10100101 A
b110 ;
b1111111101 ]
1/
1R
b111 Y
b1001010 @
b101 :
b1111111011 \
b110 X
1F
1.
1K
1$
1"
#465
0F
0.
0K
0$
0"
#470
b11010010 A
b111 ;
b1111111110 ]
b1000 Y
b10100101 @
b110 :
b1111111101 \
b111 X
1F
1.
1K
1$
1"
#475
0F
0.
0K
0$
0"
#480
b1 E
b1101001 =
b1101001 A
b1000 ;
b1111111111 ]
0/
0R
b1001 Y
b11010010 @
b111 :
b1111111110 \
b1000 X
1F
1.
1K
1$
1"
#485
0F
0.
0K
0$
0"
#490
1I
13
b1011011100 ]
b0 Y
b11 +
bx E
1%
1M
0O
b10110100 A
b1001 ;
1/
1R
b1101001 @
b1000 :
b1101001 G
b1101001 4
b1101001 <
b1111111111 \
b1001 X
1F
1.
1K
1$
1"
#495
0F
0.
0K
0$
0"
#500
0I
03
b1101101110 ]
01
0%
0M
0O
b1100111 Q
b1100111 (
b1011010 A
b0 ;
0/
0R
b1 Y
b11 +
b10110100 @
b1001 :
b1011011100 \
b0 X
b11 *
1F
1.
1K
1$
1"
#505
0F
0.
0K
0$
0"
#510
1O
01
1P
b101101 A
b1 ;
b1110110111 ]
b10 Y
b1011010 @
b0 :
b1101101110 \
b1 X
1F
1.
1K
1$
1"
#515
0F
0.
0K
0$
0"
#520
11
0P
b10010110 A
b10 ;
b1111011011 ]
1/
1R
b11 Y
b101101 @
b1 :
b1110110111 \
b10 X
1F
1.
1K
1$
1"
#525
0F
0.
0K
0$
0"
#530
b11001011 A
b11 ;
b1111101101 ]
b100 Y
b10010110 @
b10 :
b1111011011 \
b11 X
1F
1.
1K
1$
1"
#535
0F
0.
0K
0$
0"
#540
b11100101 A
b100 ;
b1111110110 ]
b101 Y
b11001011 @
b11 :
b1111101101 \
b100 X
1F
1.
1K
1$
1"
#545
0F
0.
0K
0$
0"
#550
b1110010 A
b101 ;
b1111111011 ]
0/
0R
b110 Y
b11100101 @
b100 :
b1111110110 \
b101 X
1F
1.
1K
1$
1"
#555
0F
0.
0K
0$
0"
#560
b10111001 A
b110 ;
b1111111101 ]
1/
1R
b111 Y
b1110010 @
b101 :
b1111111011 \
b110 X
1F
1.
1K
1$
1"
#565
0F
0.
0K
0$
0"
#570
b11011100 A
b111 ;
b1111111110 ]
b1000 Y
b10111001 @
b110 :
b1111111101 \
b111 X
1F
1.
1K
1$
1"
#575
0F
0.
0K
0$
0"
#580
b1 E
b1101110 =
b1101110 A
b1000 ;
b1111111111 ]
0/
0R
b1001 Y
b11011100 @
b111 :
b1111111110 \
b1000 X
1F
1.
1K
1$
1"
#585
0F
0.
0K
0$
0"
#590
1I
13
b1011001110 ]
b0 Y
b100 +
bx E
1%
1M
0O
b10110111 A
b1001 ;
1/
1R
b1101110 @
b1000 :
b1101110 G
b1101110 4
b1101110 <
b1111111111 \
b1001 X
1F
1.
1K
1$
1"
#595
0F
0.
0K
0$
0"
#600
0I
03
b1101100111 ]
01
0%
0M
0O
b100001 Q
b100001 (
b1011011 A
b0 ;
0/
0R
b1 Y
b100 +
b10110111 @
b1001 :
b1011001110 \
b0 X
b100 *
1F
1.
1K
1$
1"
#605
0F
0.
0K
0$
0"
#610
1O
01
1P
b10101101 A
b1 ;
b1110110011 ]
1/
1R
b10 Y
b1011011 @
b0 :
b1101100111 \
b1 X
1F
1.
1K
1$
1"
#615
0F
0.
0K
0$
0"
#620
11
0P
b11010110 A
b10 ;
b1111011001 ]
b11 Y
b10101101 @
b1 :
b1110110011 \
b10 X
1F
1.
1K
1$
1"
#625
0F
0.
0K
0$
0"
#630
b11101011 A
b11 ;
b1111101100 ]
b100 Y
b11010110 @
b10 :
b1111011001 \
b11 X
1F
1.
1K
1$
1"
#635
0F
0.
0K
0$
0"
#640
b1110101 A
b100 ;
b1111110110 ]
0/
0R
b101 Y
b11101011 @
b11 :
b1111101100 \
b100 X
1F
1.
1K
1$
1"
#645
0F
0.
0K
0$
0"
#650
b111010 A
b101 ;
b1111111011 ]
b110 Y
b1110101 @
b100 :
b1111110110 \
b101 X
1F
1.
1K
1$
1"
#655
0F
0.
0K
0$
0"
#660
b10011101 A
b110 ;
b1111111101 ]
1/
1R
b111 Y
b111010 @
b101 :
b1111111011 \
b110 X
1F
1.
1K
1$
1"
#665
0F
0.
0K
0$
0"
#670
b11001110 A
b111 ;
b1111111110 ]
b1000 Y
b10011101 @
b110 :
b1111111101 \
b111 X
1F
1.
1K
1$
1"
#675
0F
0.
0K
0$
0"
#680
b1 E
b1100111 =
b1100111 A
b1000 ;
b1111111111 ]
0/
0R
b1001 Y
b11001110 @
b111 :
b1111111110 \
b1000 X
1F
1.
1K
1$
1"
#685
0F
0.
0K
0$
0"
#690
1I
13
b1001000010 ]
b0 Y
b101 +
bx E
1%
1M
0O
b10110011 A
b1001 ;
1/
1R
b1100111 @
b1000 :
b1100111 G
b1100111 4
b1100111 <
b1111111111 \
b1001 X
1F
1.
1K
1$
1"
#695
0F
0.
0K
0$
0"
#700
0I
03
b1100100001 ]
01
0%
0M
0O
b1010 Q
b1010 (
b1011001 A
b0 ;
0/
0R
b1 Y
b101 +
b0 -
b10110011 @
b1001 :
b1001000010 \
b0 X
b101 *
1F
1.
1K
1$
1"
#705
0F
0.
0K
0$
0"
#710
1O
01
1P
b10101100 A
b1 ;
b1110010000 ]
1/
1R
b10 Y
b1011001 @
b0 :
b1100100001 \
b1 X
1F
1.
1K
1$
1"
#715
0F
0.
0K
0$
0"
#720
11
0P
b1010110 A
b10 ;
b1111001000 ]
0/
0R
b11 Y
b10101100 @
b1 :
b1110010000 \
b10 X
1F
1.
1K
1$
1"
#725
0F
0.
0K
0$
0"
#730
b101011 A
b11 ;
b1111100100 ]
b100 Y
b1010110 @
b10 :
b1111001000 \
b11 X
1F
1.
1K
1$
1"
#735
0F
0.
0K
0$
0"
#740
b10101 A
b100 ;
b1111110010 ]
b101 Y
b101011 @
b11 :
b1111100100 \
b100 X
1F
1.
1K
1$
1"
#745
0F
0.
0K
0$
0"
#750
b1010 A
b101 ;
b1111111001 ]
b110 Y
b10101 @
b100 :
b1111110010 \
b101 X
1F
1.
1K
1$
1"
#755
0F
0.
0K
0$
0"
#760
b10000101 A
b110 ;
b1111111100 ]
1/
1R
b111 Y
b1010 @
b101 :
b1111111001 \
b110 X
1F
1.
1K
1$
1"
#765
0F
0.
0K
0$
0"
#770
b1000010 A
b111 ;
b1111111110 ]
0/
0R
b1000 Y
b10000101 @
b110 :
b1111111100 \
b111 X
1F
1.
1K
1$
1"
#775
0F
0.
0K
0$
0"
#780
b1 E
b100001 =
b100001 A
b1000 ;
b1111111111 ]
b1001 Y
b1000010 @
b111 :
b1111111110 \
b1000 X
1F
1.
1K
1$
1"
#785
0F
0.
0K
0$
0"
#790
1I
13
b1000010100 ]
b0 Y
b0 +
b10011 -
bx E
1%
1M
0O
b10010000 A
b1001 ;
1/
1R
b100001 @
b1000 :
b100001 G
b100001 4
b100001 <
b1111111111 \
b1001 X
1F
1.
1K
1$
1"
#795
0F
0.
0K
0$
0"
#800
0I
03
b1100001010 ]
01
0%
0M
0O
b0 Q
b0 (
0N
0'
b1001000 A
b0 ;
0/
0R
b1 Y
b10010 -
b10010000 @
b1001 :
b1000010100 \
b0 X
b0 *
b10011 ,
1F
1.
1K
1$
1"
#805
0F
0.
0K
0$
0"
#810
1O
01
1P
b100100 A
b1 ;
b1110000101 ]
b10 Y
b10001 -
b1001000 @
b0 :
b1100001010 \
b1 X
b10010 ,
1F
1.
1K
1$
1"
#815
0F
0.
0K
0$
0"
#820
11
0P
b10010010 A
b10 ;
b1111000010 ]
1/
1R
b11 Y
b10000 -
b100100 @
b1 :
b1110000101 \
b10 X
b10001 ,
1F
1.
1K
1$
1"
#825
0F
0.
0K
0$
0"
#830
b1001001 A
b11 ;
b1111100001 ]
0/
0R
b100 Y
b1111 -
b10010010 @
b10 :
b1111000010 \
b11 X
b10000 ,
1F
1.
1K
1$
1"
#835
0F
0.
0K
0$
0"
#840
b10100100 A
b100 ;
b1111110000 ]
1/
1R
b101 Y
b1110 -
b1001001 @
b11 :
b1111100001 \
b100 X
b1111 ,
1F
1.
1K
1$
1"
#845
0F
0.
0K
0$
0"
#850
b1010010 A
b101 ;
b1111111000 ]
0/
0R
b110 Y
b1101 -
b10100100 @
b100 :
b1111110000 \
b101 X
b1110 ,
1F
1.
1K
1$
1"
#855
0F
0.
0K
0$
0"
#860
b101001 A
b110 ;
b1111111100 ]
b111 Y
b1100 -
b1010010 @
b101 :
b1111111000 \
b110 X
b1101 ,
1F
1.
1K
1$
1"
#865
0F
0.
0K
0$
0"
#870
b10100 A
b111 ;
b1111111110 ]
b1000 Y
b1011 -
b101001 @
b110 :
b1111111100 \
b111 X
b1100 ,
1F
1.
1K
1$
1"
#875
0F
0.
0K
0$
0"
#880
b1 E
b1010 =
b1010 A
b1000 ;
b1111111111 ]
b1001 Y
b1010 -
b10100 @
b111 :
b1111111110 \
b1000 X
b1011 ,
1F
1.
1K
1$
1"
#885
0F
0.
0K
0$
0"
#890
1I
13
bx E
1%
1M
0O
b10000101 A
b1001 ;
1/
1R
b1001 -
b1010 @
b1000 :
b1010 G
b1010 4
b1010 <
b1111111111 \
b1001 X
b1010 ,
1F
1.
1K
1$
1"
#895
0F
0.
0K
0$
0"
#900
0I
03
01
b11000010 A
b1000 -
b10000101 @
b1001 :
b1001 ,
1F
1.
1K
1$
1"
#905
0F
0.
0K
0$
0"
#910
b11100001 A
b111 -
b11000010 @
b1000 ,
1F
1.
1K
1$
1"
#915
0F
0.
0K
0$
0"
#920
b11110000 A
b110 -
b11100001 @
b111 ,
1F
1.
1K
1$
1"
#925
0F
0.
0K
0$
0"
#930
b11111000 A
b101 -
b11110000 @
b110 ,
1F
1.
1K
1$
1"
#935
0F
0.
0K
0$
0"
#940
b11111100 A
b100 -
b11111000 @
b101 ,
1F
1.
1K
1$
1"
#945
0F
0.
0K
0$
0"
#950
b11111110 A
b11 -
b11111100 @
b100 ,
1F
1.
1K
1$
1"
#955
0F
0.
0K
0$
0"
#960
b11111111 A
b10 -
b11111110 @
b11 ,
1F
1.
1K
1$
1"
#965
0F
0.
0K
0$
0"
#970
b1 -
b11111111 @
b10 ,
1F
1.
1K
1$
1"
#975
0F
0.
0K
0$
0"
#980
b0 -
b1 ,
1F
1.
1K
1$
1"
#985
0F
0.
0K
0$
0"
#990
b1010100000 ]
b0 Y
b1 +
b1010000 Q
b1010000 (
1N
1'
b0 ,
1F
1.
1K
1$
1"
#995
0F
0.
0K
0$
0"
#1000
b1101010000 ]
b1111111 A
b0 ;
0%
0M
0O
b1101001 Q
b1101001 (
0/
0R
b1 Y
b1 +
b1010100000 \
b0 X
b1 *
1F
1.
1K
1$
1"
#1005
0F
0.
0K
0$
0"
#1010
1O
01
1P
b111111 A
b1 ;
b1110101000 ]
b10 Y
b1111111 @
b0 :
b1101010000 \
b1 X
1F
1.
1K
1$
1"
#1015
0F
0.
0K
0$
0"
#1020
11
0P
b11111 A
b10 ;
b1111010100 ]
b11 Y
b111111 @
b1 :
b1110101000 \
b10 X
1F
1.
1K
1$
1"
#1025
0F
0.
0K
0$
0"
#1030
b1111 A
b11 ;
b1111101010 ]
b100 Y
b11111 @
b10 :
b1111010100 \
b11 X
1F
1.
1K
1$
1"
#1035
0F
0.
0K
0$
0"
#1040
b111 A
b100 ;
b1111110101 ]
b101 Y
b1111 @
b11 :
b1111101010 \
b100 X
1F
1.
1K
1$
1"
#1045
0F
0.
0K
0$
0"
#1050
b10000011 A
b101 ;
b1111111010 ]
1/
1R
b110 Y
b111 @
b100 :
b1111110101 \
b101 X
1F
1.
1K
1$
1"
#1055
0F
0.
0K
0$
0"
#1060
b1000001 A
b110 ;
b1111111101 ]
0/
0R
b111 Y
b10000011 @
b101 :
b1111111010 \
b110 X
1F
1.
1K
1$
1"
#1065
0F
0.
0K
0$
0"
#1070
b10100000 A
b111 ;
b1111111110 ]
1/
1R
b1000 Y
b1000001 @
b110 :
b1111111101 \
b111 X
1F
1.
1K
1$
1"
#1075
0F
0.
0K
0$
0"
#1080
b1 E
b1010000 =
b1010000 A
b1000 ;
b1111111111 ]
0/
0R
b1001 Y
b10100000 @
b111 :
b1111111110 \
b1000 X
1F
1.
1K
1$
1"
#1085
0F
0.
0K
0$
0"
#1090
1I
13
b1011010010 ]
b0 Y
b10 +
bx E
1%
1M
0O
b10101000 A
b1001 ;
1/
1R
b1010000 @
b1000 :
b1010000 G
b1010000 4
b1010000 <
b1111111111 \
b1001 X
1F
1.
1K
1$
1"
#1095
0F
0.
0K
0$
0"
#1100
0I
03
b1101101001 ]
01
0%
0M
0O
b1101110 Q
b1101110 (
b1010100 A
b0 ;
0/
0R
b1 Y
b10 +
b10101000 @
b1001 :
b1011010010 \
b0 X
b10 *
1F
1.
1K
1$
1"
#1105
0F
0.
0K
0$
0"
#1110
1O
01
1P
b10101010 A
b1 ;
b1110110100 ]
1/
1R
b10 Y
b1010100 @
b0 :
b1101101001 \
b1 X
1F
1.
1K
1$
1"
#1115
0F
0.
0K
0$
0"
#1120
11
0P
b1010101 A
b10 ;
b1111011010 ]
0/
0R
b11 Y
b10101010 @
b1 :
b1110110100 \
b10 X
1F
1.
1K
1$
1"
#1125
0F
0.
0K
0$
0"
#1130
b101010 A
b11 ;
b1111101101 ]
b100 Y
b1010101 @
b10 :
b1111011010 \
b11 X
1F
1.
1K
1$
1"
#1135
0F
0.
0K
0$
0"
#1140
b10010101 A
b100 ;
b1111110110 ]
1/
1R
b101 Y
b101010 @
b11 :
b1111101101 \
b100 X
1F
1.
1K
1$
1"
#1145
0F
0.
0K
0$
0"
#1150
b1001010 A
b101 ;
b1111111011 ]
0/
0R
b110 Y
b10010101 @
b100 :
b1111110110 \
b101 X
1F
1.
1K
1$
1"
#1155
0F
0.
0K
0$
0"
#1160
b10100101 A
b110 ;
b1111111101 ]
1/
1R
b111 Y
b1001010 @
b101 :
b1111111011 \
b110 X
1F
1.
1K
1$
1"
#1165
0F
0.
0K
0$
0"
