uart/bench.v
`default_nettype none
`timescale 1 ns/1 ns

//==============================================================================

module simple_message
(
  input  logic      _clock,
  input  logic      _reset,
  output logic[7:0] _out,
  output logic      _valid,
  input  logic      _ready
);

  localparam delay_max = 20;

  logic[7:0] text[0:5];
  logic[7:0] delay, delay_;
  logic[7:0] cursor, cursor_;

  initial begin
    $readmemh("ping.hex", text);
    delay  = delay_max;
    cursor = 0;
  end

  always_comb begin
    if (_reset) begin
      delay_  = delay_max;
      cursor_ = 0;
    end else if (delay) begin
      delay_  = delay - 1;
      cursor_ = cursor;
    end else if (_valid && _ready) begin
      delay_  = cursor == 5 ? delay_max - 1 : delay;
      cursor_ = cursor == 5 ? 0 : cursor + 1;
    end else begin
      delay_  = delay;
      cursor_ = cursor;
    end
  end

  always @(posedge _clock) begin
    delay  <= delay_;
    cursor <= cursor_;
  end

  assign _out   = _reset ? 0 : delay ? 0 : text[cursor];
  assign _valid = _reset ? 0 : (delay == 0);

endmodule

//==============================================================================

module simple_tx
#(
  parameter clocks_per_bit
)
(
  input logic      _clock,
  input logic      _reset,
  input logic[7:0] _tx_in,
  input logic      _tx_valid,
  output logic     _tx_ready,
  output logic     _tx_out
);

  localparam bits_per_byte = 10; // 1 start + 8 data + 1 stop
  localparam delay_mid = clocks_per_bit / 2;
  localparam delay_max = clocks_per_bit - 1;
  localparam count_max = bits_per_byte - 1; // 1 start + 8 data + 9 stop to make sure we're really stopped :D

  logic[7:0] tx_delay, tx_delay_;
  logic[7:0] tx_count, tx_count_;
  logic[9:0] tx_shift, tx_shift_;

  initial begin
    tx_delay = delay_max;
    tx_count = count_max;
    tx_shift = 10'b1111111111;
  end

  assign _tx_ready = !_reset && tx_delay == delay_max && tx_count == count_max;
  assign _tx_out   = tx_shift[0];

  wire _tx_bit   = tx_delay == 0 && tx_count > 0 && tx_count < count_max;
  wire _tx_byte  = tx_delay == 0 && tx_count == 1;

  always_comb begin
    if (_reset) begin
      tx_delay_ = delay_max;
      tx_count_ = count_max;
    end else if (tx_delay < delay_max) begin
      tx_delay_ = tx_delay + 1;
      tx_count_ = tx_count;
    end else if (tx_count < count_max) begin
      tx_delay_ = 0;
      tx_count_ = tx_count + 1;
    end else if (_tx_valid && _tx_ready) begin
      tx_delay_ = 0;
      tx_count_ = 0;
    end
  end

  always_comb begin
    if (_reset) begin
      tx_shift_ = 10'b1111111111;
    end else if (_tx_valid && _tx_ready) begin
      tx_shift_ = { 1'b1, _tx_in, 1'b0 };
    end else if (tx_delay_ == 0) begin
      tx_shift_ = { 1'b1, tx_shift[9:1] };
    end else begin
      tx_shift_ = tx_shift;
    end
  end

  always @(posedge _clock) begin
    tx_delay <= tx_delay_;
    tx_count <= tx_count_;
    tx_shift <= tx_shift_;
  end

endmodule

//==============================================================================

module simple_rx
#(
  parameter clocks_per_bit
)
(
  input logic       _clock,
  input logic       _reset,

  input logic       _rx_in,

  output logic[7:0] _rx_out,
  output logic      _rx_valid,
  input logic       _rx_ready
);

  localparam bits_per_byte = 10; // 1 start + 8 data + 1 stop
  localparam delay_mid = clocks_per_bit / 2;
  localparam delay_max = clocks_per_bit - 1;
  localparam count_max = bits_per_byte - 1; // 1 start + 8 data + 9 stop to make sure we're really stopped :D

  logic[7:0] rx_delay, rx_delay_;
  logic[7:0] rx_count, rx_count_;

  logic[7:0] rx_shift, rx_shift_;
  logic[7:0] rx_data,  rx_data_;

  initial begin
    rx_delay = delay_max;
    rx_count = count_max;
    rx_shift = 0;
    rx_data  = 0;
  end

  assign _rx_ready = !_reset;
  assign _rx_valid = _reset ? 0 : rx_delay == delay_mid && rx_count == count_max - 1;
  assign _rx_out   = rx_data;

  //----------------------------------------

  always_comb begin
    if (_reset) begin
      rx_delay_ = delay_max;
      rx_count_ = count_max;
    end else if (rx_delay < delay_max) begin
      rx_delay_ = rx_delay + 1;
    end else if (rx_count < count_max) begin
      rx_delay_ = 0;
      rx_count_ = rx_count + 1;
    end else if (_rx_in == 0) begin
      rx_delay_ = 0;
      rx_count_ = 0;
    end else begin
      rx_delay_ = rx_delay;
      rx_count_ = rx_count;
    end
  end

  //----------------------------------------

  always_comb begin
    if (_reset)
      rx_data_  = 0;
    else if (rx_delay_ == delay_mid && rx_count_ == count_max - 1)
      rx_data_  = rx_shift_;
    else
      rx_data_ = rx_data;
  end

  //----------------------------------------

  always_comb begin
    if (_reset)
      rx_shift_ = 0;
    else if (rx_delay_ == delay_mid)
      rx_shift_ = {_rx_in, rx_shift[7:1]};
    else
      rx_shift_ = rx_shift;
  end

  //----------------------------------------

  always @(posedge _clock) begin
    rx_data  <= rx_data_;
    rx_delay <= rx_delay_;
    rx_count <= rx_count_;
    rx_shift <= rx_shift_;
  end

  wire _rx_bit = rx_delay == delay_mid && rx_count > 0 && rx_count < count_max;


endmodule

//==============================================================================

module bench();

  logic clock = 1;
  logic reset = 1;

  always #5 clock = ~clock;

  initial begin
    $dumpfile ("bench.vcd");
    $dumpvars;

    #95;
    reset = 0;

    #8000 $finish();
  end

  //----------------------------------------------------------------------------

  localparam clocks_per_bit = 1;

  simple_message msg();

  assign msg._clock = clock;
  assign msg._reset = reset;
  assign msg._ready = tx._tx_ready;

  simple_tx #(.clocks_per_bit(clocks_per_bit)) tx();

  assign tx._clock    = clock;
  assign tx._reset    = reset;
  assign tx._tx_in    = msg._out;
  assign tx._tx_valid = msg._valid;

  simple_rx #(.clocks_per_bit(clocks_per_bit)) rx();

  assign rx._clock = clock;
  assign rx._reset = reset;
  assign rx._rx_in = tx._tx_out;

  //----------------------------------------------------------------------------

endmodule

//==============================================================================

uart/bench.vcd
$date
	Mon Jul 29 21:02:20 2024
$end
$version
	Icarus Verilog
$end
$timescale
	1ns
$end
$scope module bench $end
$var parameter 32 ! clocks_per_bit $end
$var reg 1 " clock $end
$var reg 1 # reset $end
$scope module msg $end
$var wire 1 $ _clock $end
$var wire 1 % _ready $end
$var wire 1 & _reset $end
$var wire 1 ' _valid $end
$var wire 8 ( _out [7:0] $end
$var parameter 32 ) delay_max $end
$var reg 8 * cursor [7:0] $end
$var reg 8 + cursor_ [7:0] $end
$var reg 8 , delay [7:0] $end
$var reg 8 - delay_ [7:0] $end
$upscope $end
$scope module rx $end
$var wire 1 . _clock $end
$var wire 1 / _reset $end
$var wire 1 0 _rx_bit $end
$var wire 1 1 _rx_in $end
$var wire 8 2 _rx_out [7:0] $end
$var wire 1 3 _rx_valid $end
$var wire 1 4 _rx_ready $end
$var parameter 32 5 bits_per_byte $end
$var parameter 32 6 clocks_per_bit $end
$var parameter 33 7 count_max $end
$var parameter 33 8 delay_max $end
$var parameter 32 9 delay_mid $end
$var reg 8 : rx_count [7:0] $end
$var reg 8 ; rx_count_ [7:0] $end
$var reg 8 < rx_data [7:0] $end
$var reg 8 = rx_data_ [7:0] $end
$var reg 8 > rx_delay [7:0] $end
$var reg 8 ? rx_delay_ [7:0] $end
$var reg 8 @ rx_shift [7:0] $end
$var reg 8 A rx_shift_ [7:0] $end
$upscope $end
$scope module tx $end
$var wire 1 B _clock $end
$var wire 1 C _reset $end
$var wire 1 D _tx_bit $end
$var wire 1 E _tx_byte $end
$var wire 8 F _tx_in [7:0] $end
$var wire 1 G _tx_ready $end
$var wire 1 H _tx_valid $end
$var wire 1 I _tx_out $end
$var parameter 32 J bits_per_byte $end
$var parameter 32 K clocks_per_bit $end
$var parameter 33 L count_max $end
$var parameter 33 M delay_max $end
$var parameter 32 N delay_mid $end
$var reg 8 O tx_count [7:0] $end
$var reg 8 P tx_count_ [7:0] $end
$var reg 8 Q tx_delay [7:0] $end
$var reg 8 R tx_delay_ [7:0] $end
$var reg 10 S tx_shift [9:0] $end
$var reg 10 T tx_shift_ [9:0] $end
$upscope $end
$upscope $end
$enddefinitions $end
$comment Show the parameter values. $end
$dumpall
b0 N
b0 M
b1001 L
b1 K
b1010 J
b0 9
b0 8
b1001 7
b1 6
b1010 5
b10100 )
b1 !
$end
#0
$dumpvars
b1111111111 T
b1111111111 S
b0 R
b0 Q
b1001 P
b1001 O
1I
0H
0G
b0 F
0E
0D
1C
1B
b0 A
b0 @
b0 ?
b0 >
b0 =
b0 <
b1001 ;
b1001 :
04
03
b0 2
11
00
1/
1.
b10100 -
b10100 ,
b0 +
b0 *
b0 (
0'
1&
0%
1$
1#
1"
$end
#5
0.
0B
0$
0"
#10
1.
1B
1$
1"
#15
0.
0B
0$
0"
#20
1.
1B
1$
1"
#25
0.
0B
0$
0"
#30
1.
1B
1$
1"
#35
0.
0B
0$
0"
#40
1.
1B
1$
1"
#45
0.
0B
0$
0"
#50
1.
1B
1$
1"
#55
0.
0B
0$
0"
#60
1.
1B
1$
1"
#65
0.
0B
0$
0"
#70
1.
1B
1$
1"
#75
0.
0B
0$
0"
#80
1.
1B
1$
1"
#85
0.
0B
0$
0"
#90
1.
1B
1$
1"
#95
1%
1G
b10000000 A
b10011 -
0.
0B
0$
0"
14
0/
0C
0&
0#
#100
b11000000 A
b10010 -
b10000000 @
b10011 ,
1.
1B
1$
1"
#105
0.
0B
0$
0"
#110
b11100000 A
b10001 -
b11000000 @
b10010 ,
1.
1B
1$
1"
#115
0.
0B
0$
0"
#120
b11110000 A
b10000 -
b11100000 @
b10001 ,
1.
1B
1$
1"
#125
0.
0B
0$
0"
#130
b11111000 A
b1111 -
b11110000 @
b10000 ,
1.
1B
1$
1"
#135
0.
0B
0$
0"
#140
b11111100 A
b1110 -
b11111000 @
b1111 ,
1.
1B
1$
1"
#145
0.
0B
0$
0"
#150
b11111110 A
b1101 -
b11111100 @
b1110 ,
1.
1B
1$
1"
#155
0.
0B
0$
0"
#160
b11111111 A
b1100 -
b11111110 @
b1101 ,
1.
1B
1$
1"
#165
0.
0B
0$
0"
#170
b1011 -
b11111111 @
b1100 ,
1.
1B
1$
1"
#175
0.
0B
0$
0"
#180
b1010 -
b1011 ,
1.
1B
1$
1"
#185
0.
0B
0$
0"
#190
b1001 -
b1010 ,
1.
1B
1$
1"
#195
0.
0B
0$
0"
#200
b1000 -
b1001 ,
1.
1B
1$
1"
#205
0.
0B
0$
0"
#210
b111 -
b1000 ,
1.
1B
1$
1"
#215
0.
0B
0$
0"
#220
b110 -
b111 ,
1.
1B
1$
1"
#225
0.
0B
0$
0"
#230
b101 -
b110 ,
1.
1B
1$
1"
#235
0.
0B
0$
0"
#240
b100 -
b101 ,
1.
1B
1$
1"
#245
0.
0B
0$
0"
#250
b11 -
b100 ,
1.
1B
1$
1"
#255
0.
0B
0$
0"
#260
b10 -
b11 ,
1.
1B
1$
1"
#265
0.
0B
0$
0"
#270
b1 -
b10 ,
1.
1B
1$
1"
#275
0.
0B
0$
0"
#280
b0 -
b1 ,
1.
1B
1$
1"
#285
0.
0B
0$
0"
#290
b1010100000 T
b0 P
b1 +
b1010000 F
b1010000 (
1H
1'
b0 ,
1.
1B
1$
1"
#295
0.
0B
0$
0"
#300
b1101010000 T
b1111111 A
b0 ;
0%
0G
0D
b1101001 F
b1101001 (
01
0I
b1 P
b1 +
b1010100000 S
b0 O
b1 *
1.
1B
1$
1"
#305
0.
0B
0$
0"
#310
1D
00
1E
b111111 A
b1 ;
b1110101000 T
b10 P
b1111111 @
b0 :
b1101010000 S
b1 O
1.
1B
1$
1"
#315
0.
0B
0$
0"
#320
10
0E
b11111 A
b10 ;
b1111010100 T
b11 P
b111111 @
b1 :
b1110101000 S
b10 O
1.
1B
1$
1"
#325
0.
0B
0$
0"
#330
b1111 A
b11 ;
b1111101010 T
b100 P
b11111 @
b10 :
b1111010100 S
b11 O
1.
1B
1$
1"
#335
0.
0B
0$
0"
#340
b111 A
b100 ;
b1111110101 T
b101 P
b1111 @
b11 :
b1111101010 S
b100 O
1.
1B
1$
1"
#345
0.
0B
0$
0"
#350
b10000011 A
b101 ;
b1111111010 T
11
1I
b110 P
b111 @
b100 :
b1111110101 S
b101 O
1.
1B
1$
1"
#355
0.
0B
0$
0"
#360
b1000001 A
b110 ;
b1111111101 T
01
0I
b111 P
b10000011 @
b101 :
b1111111010 S
b110 O
1.
1B
1$
1"
#365
0.
0B
0$
0"
#370
b10100000 A
b111 ;
b1111111110 T
11
1I
b1000 P
b1000001 @
b110 :
b1111111101 S
b111 O
1.
1B
1$
1"
#375
0.
0B
0$
0"
#380
b1010000 =
b1010000 A
b1000 ;
b1111111111 T
01
0I
b1001 P
b10100000 @
b111 :
b1111111110 S
b1000 O
1.
1B
1$
1"
#385
0.
0B
0$
0"
#390
13
b1011010010 T
b0 P
b10 +
1%
1G
0D
b10101000 A
b1001 ;
11
1I
b1010000 @
b1000 :
b1010000 2
b1010000 <
b1111111111 S
b1001 O
1.
1B
1$
1"
#395
0.
0B
0$
0"
#400
03
b1101101001 T
00
0%
0G
0D
b1101110 F
b1101110 (
b1010100 A
b0 ;
01
0I
b1 P
b10 +
b10101000 @
b1001 :
b1011010010 S
b0 O
b10 *
1.
1B
1$
1"
#405
0.
0B
0$
0"
#410
1D
00
1E
b10101010 A
b1 ;
b1110110100 T
11
1I
b10 P
b1010100 @
b0 :
b1101101001 S
b1 O
1.
1B
1$
1"
#415
0.
0B
0$
0"
#420
10
0E
b1010101 A
b10 ;
b1111011010 T
01
0I
b11 P
b10101010 @
b1 :
b1110110100 S
b10 O
1.
1B
1$
1"
#425
0.
0B
0$
0"
#430
b101010 A
b11 ;
b1111101101 T
b100 P
b1010101 @
b10 :
b1111011010 S
b11 O
1.
1B
1$
1"
#435
0.
0B
0$
0"
#440
b10010101 A
b100 ;
b1111110110 T
11
1I
b101 P
b101010 @
b11 :
b1111101101 S
b100 O
1.
1B
1$
1"
#445
0.
0B
0$
0"
#450
b1001010 A
b101 ;
b1111111011 T
01
0I
b110 P
b10010101 @
b100 :
b1111110110 S
b101 O
1.
1B
1$
1"
#455
0.
0B
0$
0"
#460
b10100101 A
b110 ;
b1111111101 T
11
1I
b111 P
b1001010 @
b101 :
b1111111011 S
b110 O
1.
1B
1$
1"
#465
0.
0B
0$
0"
#470
b11010010 A
b111 ;
b1111111110 T
b1000 P
b10100101 @
b110 :
b1111111101 S
b111 O
1.
1B
1$
1"
#475
0.
0B
0$
0"
#480
b1101001 =
b1101001 A
b1000 ;
b1111111111 T
01
0I
b1001 P
b11010010 @
b111 :
b1111111110 S
b1000 O
1.
1B
1$
1"
#485
0.
0B
0$
0"
#490
13
b1011011100 T
b0 P
b11 +
1%
1G
0D
b10110100 A
b1001 ;
11
1I
b1101001 @
b1000 :
b1101001 2
b1101001 <
b1111111111 S
b1001 O
1.
1B
1$
1"
#495
0.
0B
0$
0"
#500
03
b1101101110 T
00
0%
0G
0D
b1100111 F
b1100111 (
b1011010 A
b0 ;
01
0I
b1 P
b11 +
b10110100 @
b1001 :
b1011011100 S
b0 O
b11 *
1.
1B
1$
1"
#505
0.
0B
0$
0"
#510
1D
00
1E
b101101 A
b1 ;
b1110110111 T
b10 P
b1011010 @
b0 :
b1101101110 S
b1 O
1.
1B
1$
1"
#515
0.
0B
0$
0"
#520
10
0E
b10010110 A
b10 ;
b1111011011 T
11
1I
b11 P
b101101 @
b1 :
b1110110111 S
b10 O
1.
1B
1$
1"
#525
0.
0B
0$
0"
#530
b11001011 A
b11 ;
b1111101101 T
b100 P
b10010110 @
b10 :
b1111011011 S
b11 O
1.
1B
1$
1"
#535
0.
0B
0$
0"
#540
b11100101 A
b100 ;
b1111110110 T
b101 P
b11001011 @
b11 :
b1111101101 S
b100 O
1.
1B
1$
1"
#545
0.
0B
0$
0"
#550
b1110010 A
b101 ;
b1111111011 T
01
0I
b110 P
b11100101 @
b100 :
b1111110110 S
b101 O
1.
1B
1$
1"
#555
0.
0B
0$
0"
#560
b10111001 A
b110 ;
b1111111101 T
11
1I
b111 P
b1110010 @
b101 :
b1111111011 S
b110 O
1.
1B
1$
1"
#565
0.
0B
0$
0"
#570
b11011100 A
b111 ;
b1111111110 T
b1000 P
b10111001 @
b110 :
b1111111101 S
b111 O
1.
1B
1$
1"
#575
0.
0B
0$
0"
#580
b1101110 =
b1101110 A
b1000 ;
b1111111111 T
01
0I
b1001 P
b11011100 @
b111 :
b1111111110 S
b1000 O
1.
1B
1$
1"
#585
0.
0B
0$
0"
#590
13
b1011001110 T
b0 P
b100 +
1%
1G
0D
b10110111 A
b1001 ;
11
1I
b1101110 @
b1000 :
b1101110 2
b1101110 <
b1111111111 S
b1001 O
1.
1B
1$
1"
#595
0.
0B
0$
0"
#600
03
b1101100111 T
00
0%
0G
0D
b100001 F
b100001 (
b1011011 A
b0 ;
01
0I
b1 P
b100 +
b10110111 @
b1001 :
b1011001110 S
b0 O
b100 *
1.
1B
1$
1"
#605
0.
0B
0$
0"
#610
1D
00
1E
b10101101 A
b1 ;
b1110110011 T
11
1I
b10 P
b1011011 @
b0 :
b1101100111 S
b1 O
1.
1B
1$
1"
#615
0.
0B
0$
0"
#620
10
0E
b11010110 A
b10 ;
b1111011001 T
b11 P
b10101101 @
b1 :
b1110110011 S
b10 O
1.
1B
1$
1"
#625
0.
0B
0$
0"
#630
b11101011 A
b11 ;
b1111101100 T
b100 P
b11010110 @
b10 :
b1111011001 S
b11 O
1.
1B
1$
1"
#635
0.
0B
0$
0"
#640
b1110101 A
b100 ;
b1111110110 T
01
0I
b101 P
b11101011 @
b11 :
b1111101100 S
b100 O
1.
1B
1$
1"
#645
0.
0B
0$
0"
#650
b111010 A
b101 ;
b1111111011 T
b110 P
b1110101 @
b100 :
b1111110110 S
b101 O
1.
1B
1$
1"
#655
0.
0B
0$
0"
#660
b10011101 A
b110 ;
b1111111101 T
11
1I
b111 P
b111010 @
b101 :
b1111111011 S
b110 O
1.
1B
1$
1"
#665
0.
0B
0$
0"
#670
b11001110 A
b111 ;
b1111111110 T
b1000 P
b10011101 @
b110 :
b1111111101 S
b111 O
1.
1B
1$
1"
#675
0.
0B
0$
0"
#680
b1100111 =
b1100111 A
b1000 ;
b1111111111 T
01
0I
b1001 P
b11001110 @
b111 :
b1111111110 S
b1000 O
1.
1B
1$
1"
#685
0.
0B
0$
0"
#690
13
b1001000010 T
b0 P
b101 +
1%
1G
0D
b10110011 A
b1001 ;
11
1I
b1100111 @
b1000 :
b1100111 2
b1100111 <
b1111111111 S
b1001 O
1.
1B
1$
1"
#695
0.
0B
0$
0"
#700
03
b1100100001 T
00
0%
0G
0D
b1010 F
b1010 (
b1011001 A
b0 ;
01
0I
b1 P
b101 +
b0 -
b10110011 @
b1001 :
b1001000010 S
b0 O
b101 *
1.
1B
1$
1"
#705
0.
0B
0$
0"
#710
1D
00
1E
b10101100 A
b1 ;
b1110010000 T
11
1I
b10 P
b1011001 @
b0 :
b1100100001 S
b1 O
1.
1B
1$
1"
#715
0.
0B
0$
0"
#720
10
0E
b1010110 A
b10 ;
b1111001000 T
01
0I
b11 P
b10101100 @
b1 :
b1110010000 S
b10 O
1.
1B
1$
1"
#725
0.
0B
0$
0"
#730
b101011 A
b11 ;
b1111100100 T
b100 P
b1010110 @
b10 :
b1111001000 S
b11 O
1.
1B
1$
1"
#735
0.
0B
0$
0"
#740
b10101 A
b100 ;
b1111110010 T
b101 P
b101011 @
b11 :
b1111100100 S
b100 O
1.
1B
1$
1"
#745
0.
0B
0$
0"
#750
b1010 A
b101 ;
b1111111001 T
b110 P
b10101 @
b100 :
b1111110010 S
b101 O
1.
1B
1$
1"
#755
0.
0B
0$
0"
#760
b10000101 A
b110 ;
b1111111100 T
11
1I
b111 P
b1010 @
b101 :
b1111111001 S
b110 O
1.
1B
1$
1"
#765
0.
0B
0$
0"
#770
b1000010 A
b111 ;
b1111111110 T
01
0I
b1000 P
b10000101 @
b110 :
b1111111100 S
b111 O
1.
1B
1$
1"
#775
0.
0B
0$
0"
#780
b100001 =
b100001 A
b1000 ;
b1111111111 T
b1001 P
b1000010 @
b111 :
b1111111110 S
b1000 O
1.
1B
1$
1"
#785
0.
0B
0$
0"
#790
13
b1000010100 T
b0 P
b0 +
b10011 -
1%
1G
0D
b10010000 A
b1001 ;
11
1I
b100001 @
b1000 :
b100001 2
b100001 <
b1111111111 S
b1001 O
1.
1B
1$
1"
#795
0.
0B
0$
0"
#800
03
b1100001010 T
00
0%
0G
0D
b0 F
b0 (
0H
0'
b1001000 A
b0 ;
01
0I
b1 P
b10010 -
b10010000 @
b1001 :
b1000010100 S
b0 O
b0 *
b10011 ,
1.
1B
1$
1"
#805
0.
0B
0$
0"
#810
1D
00
1E
b100100 A
b1 ;
b1110000101 T
b10 P
b10001 -
b1001000 @
b0 :
b1100001010 S
b1 O
b10010 ,
1.
1B
1$
1"
#815
0.
0B
0$
0"
#820
10
0E
b10010010 A
b10 ;
b1111000010 T
11
1I
b11 P
b10000 -
b100100 @
b1 :
b1110000101 S
b10 O
b10001 ,
1.
1B
1$
1"
#825
0.
0B
0$
0"
#830
b1001001 A
b11 ;
b1111100001 T
01
0I
b100 P
b1111 -
b10010010 @
b10 :
b1111000010 S
b11 O
b10000 ,
1.
1B
1$
1"
#835
0.
0B
0$
0"
#840
b10100100 A
b100 ;
b1111110000 T
11
1I
b101 P
b1110 -
b1001001 @
b11 :
b1111100001 S
b100 O
b1111 ,
1.
1B
1$
1"
#845
0.
0B
0$
0"
#850
b1010010 A
b101 ;
b1111111000 T
01
0I
b110 P
b1101 -
b10100100 @
b100 :
b1111110000 S
b101 O
b1110 ,
1.
1B
1$
1"
#855
0.
0B
0$
0"
#860
b101001 A
b110 ;
b1111111100 T
b111 P
b1100 -
b1010010 @
b101 :
b1111111000 S
b110 O
b1101 ,
1.
1B
1$
1"
#865
0.
0B
0$
0"
#870
b10100 A
b111 ;
b1111111110 T
b1000 P
b1011 -
b101001 @
b110 :
b1111111100 S
b111 O
b1100 ,
1.
1B
1$
1"
#875
0.
0B
0$
0"
#880
b1010 =
b1010 A
b1000 ;
b1111111111 T
b1001 P
b1010 -
b10100 @
b111 :
b1111111110 S
b1000 O
b1011 ,
1.
1B
1$
1"
#885
0.
0B
0$
0"
#890
13
1%
1G
0D
b10000101 A
b1001 ;
11
1I
b1001 -
b1010 @
b1000 :
b1010 2
b1010 <
b1111111111 S
b1001 O
b1010 ,
1.
1B
1$
1"
#895
0.
0B
0$
0"
#900
03
00
b11000010 A
b1000 -
b10000101 @
b1001 :
b1001 ,
1.
1B
1$
1"
#905
0.
0B
0$
0"
#910
b11100001 A
b111 -
b11000010 @
b1000 ,
1.
1B
1$
1"
#915
0.
0B
0$
0"
#920
b11110000 A
b110 -
b11100001 @
b111 ,
1.
1B
1$
1"
#925
0.
0B
0$
0"
#930
b11111000 A
b101 -
b11110000 @
b110 ,
1.
1B
1$
1"
#935
0.
0B
0$
0"
#940
b11111100 A
b100 -
b11111000 @
b101 ,
1.
1B
1$
1"
#945
0.
0B
0$
0"
#950
b11111110 A
b11 -
b11111100 @
b100 ,
1.
1B
1$
1"
#955
0.
0B
0$
0"
#960
b11111111 A
b10 -
b11111110 @
b11 ,
1.
1B
1$
1"
#965
0.
0B
0$
0"
#970
b1 -
b11111111 @
b10 ,
1.
1B
1$
1"
#975
0.
0B
0$
0"
#980
b0 -
b1 ,
1.
1B
1$
1"
#985
0.
0B
0$
0"
#990
b1010100000 T
b0 P
b1 +
b1010000 F
b1010000 (
1H
1'
b0 ,
1.
1B
1$
1"
#995
0.
0B
0$
0"
#1000
b1101010000 T
b1111111 A
b0 ;
0%
0G
0D
b1101001 F
b1101001 (
01
0I
b1 P
b1 +
b1010100000 S
b0 O
b1 *
1.
1B
1$
1"
#1005
0.
0B
0$
0"
#1010
1D
00
1E
b111111 A
b1 ;
b1110101000 T
b10 P
b1111111 @
b0 :
b1101010000 S
b1 O
1.
1B
1$
1"
#1015
0.
0B
0$
0"
#1020
10
0E
b11111 A
b10 ;
b1111010100 T
b11 P
b111111 @
b1 :
b1110101000 S
b10 O
1.
1B
1$
1"
#1025
0.
0B
0$
0"
#1030
b1111 A
b11 ;
b1111101010 T
b100 P
b11111 @
b10 :
b1111010100 S
b11 O
1.
1B
1$
1"
#1035
0.
0B
0$
0"
#1040
b111 A
b100 ;
b1111110101 T
b101 P
b1111 @
b11 :
b1111101010 S
b100 O
1.
1B
1$
1"
#1045
0.
0B
0$
0"
#1050
b10000011 A
b101 ;
b1111111010 T
11
1I
b110 P
b111 @
b100 :
b1111110101 S
b101 O
1.
1B
1$
1"
#1055
0.
0B
0$
0"
#1060
b1000001 A
b110 ;
b1111111101 T
01
0I
b111 P
b10000011 @
b101 :
b1111111010 S
b110 O
1.
1B
1$
1"
#1065
0.
0B
0$
0"
#1070
b10100000 A
b111 ;
b1111111110 T
11
1I
b1000 P
b1000001 @
b110 :
b1111111101 S
b111 O
1.
1B
1$
1"
#1075
0.
0B
0$
0"
#1080
b1010000 =
b1010000 A
b1000 ;
b1111111111 T
01
0I
b1001 P
b10100000 @
b111 :
b1111111110 S
b1000 O
1.
1B
1$
1"
#1085
0.
0B
0$
0"
#1090
13
b1011010010 T
b0 P
b10 +
1%
1G
0D
b10101000 A
b1001 ;
11
1I
b1010000 @
b1000 :
b1010000 2
b1010000 <
b1111111111 S
b1001 O
1.
1B
1$
1"
#1095
0.
0B
0$
0"
#1100
03
b1101101001 T
00
0%
0G
0D
b1101110 F
b1101110 (
b1010100 A
b0 ;
01
0I
b1 P
b10 +
b10101000 @
b1001 :
b1011010010 S
b0 O
b10 *
1.
1B
1$
1"
#1105
0.
0B
0$
0"
#1110
1D
00
1E
b10101010 A
b1 ;
b1110110100 T
11
1I
b10 P
b1010100 @
b0 :
b1101101001 S
b1 O
1.
1B
1$
1"
#1115
0.
0B
0$
0"
#1120
10
0E
b1010101 A
b10 ;
b1111011010 T
01
0I
b11 P
b10101010 @
b1 :
b1110110100 S
b10 O
1.
1B
1$
1"
#1125
0.
0B
0$
0"
#1130
b101010 A
b11 ;
b1111101101 T
b100 P
b1010101 @
b10 :
b1111011010 S
b11 O
1.
1B
1$
1"
#1135
0.
0B
0$
0"
#1140
b10010101 A
b100 ;
b1111110110 T
11
1I
b101 P
b101010 @
b11 :
b1111101101 S
b100 O
1.
1B
1$
1"
#1145
0.
0B
0$
0"
#1150
b1001010 A
b101 ;
b1111111011 T
01
0I
b110 P
b10010101 @
b100 :
b1111110110 S
b101 O
1.
1B
1$
1"
#1155
0.
0B
0$
0"
#1160
b10100101 A
b110 ;
b1111111101 T
11
1I
b111 P
b1001010 @
b101 :
b1111111011 S
b110 O
1.
1B
1$
1"
#1165
0.
0B
0$
0"
#1170
b11010010 A
b111 ;
b1111111110 T
b1000 P
b10100101 @
b110 :
b1111111101 S
b111 O
1.
1B
1$
1"
#1175
0.
0B
0$
0"
#1180
b1101001 =
b1101001 A
b1000 ;
b1111111111 T
01
0I
b1001 P
b11010010 @
b111 :
b1111111110 S
b1000 O
1.
1B
1$
1"
#1185
0.
0B
0$
0"
#1190
13
b1011011100 T
b0 P
b11 +
1%
1G
0D
b10110100 A
b1001 ;
11
1I
b1101001 @
b1000 :
b1101001 2
b1101001 <
b1111111111 S
b1001 O
1.
1B
1$
1"
#1195
0.
0B
0$
0"
#1200
03
b1101101110 T
00
0%
0G
0D
b1100111 F
b1100111 (
b1011010 A
b0 ;
01
0I
b1 P
b11 +
b10110100 @
b1001 :
b1011011100 S
b0 O
b11 *
1.
1B
1$
1"
#1205
0.
0B
0$
0"
#1210
1D
00
1E
b101101 A
b1 ;
b1110110111 T
b10 P
b1011010 @
b0 :
b1101101110 S
b1 O
1.
1B
1$
1"
#1215
0.
0B
0$
0"
#1220
10
0E
b10010110 A
b10 ;
b1111011011 T
11
1I
b11 P
b101101 @
b1 :
b1110110111 S
b10 O
1.
1B
1$
1"
#1225
0.
0B
0$
0"
#1230
b11001011 A
b11 ;
b1111101101 T
b100 P
b10010110 @
b10 :
b1111011011 S
b11 O
1.
1B
1$
1"
#1235
0.
0B
0$
0"
#1240
b11100101 A
b100 ;
b1111110110 T
b101 P
b11001011 @
b11 :
b1111101101 S
b100 O
1.
1B
1$
1"
#1245
0.
0B
0$
0"
#1250
b1110010 A
b101 ;
b1111111011 T
01
0I
b110 P
b11100101 @
b100 :
b1111110110 S
b101 O
1.
1B
1$
1"
#1255
0.
0B
0$
0"
#1260
b10111001 A
b110 ;
b1111111101 T
11
1I
b111 P
b1110010 @
b101 :
b1111111011 S
b110 O
1.
1B
1$
1"
#1265
0.
0B
0$
0"
#1270
b11011100 A
b111 ;
b1111111110 T
b1000 P
b10111001 @
b110 :
b1111111101 S
b111 O
1.
1B
1$
1"
#1275
0.
0B
0$
0"
#1280
b1101110 =
b1101110 A
b1000 ;
b1111111111 T
01
0I
b1001 P
b11011100 @
b111 :
b1111111110 S
b1000 O
1.
1B
1$
1"
#1285
0.
0B
0$
0"
#1290
13
b1011001110 T
b0 P
b100 +
1%
1G
0D
b10110111 A
b1001 ;
11
1I
b1101110 @
b1000 :
b1101110 2
b1101110 <
b1111111111 S
b1001 O
1.
1B
1$
1"
#1295
0.
0B
0$
0"
#1300
03
b1101100111 T
00
0%
0G
0D
b100001 F
b100001 (
b1011011 A
b0 ;
01
0I
b1 P
b100 +
b10110111 @
b1001 :
b1011001110 S
b0 O
b100 *
1.
1B
1$
1"
#1305
0.
0B
0$
0"
#1310
1D
00
1E
b10101101 A
b1 ;
b1110110011 T
11
1I
b10 P
b1011011 @
b0 :
b1101100111 S
b1 O
1.
1B
1$
1"
#1315
0.
0B
0$
0"
#1320
10
0E
b11010110 A
b10 ;
b1111011001 T
b11 P
b10101101 @
b1 :
b1110110011 S
b10 O
1.
1B
1$
1"
#1325
0.
0B
0$
0"
#1330
b11101011 A
b11 ;
b1111101100 T
b100 P
b11010110 @
b10 :
b1111011001 S
b11 O
1.
1B
1$
1"
#1335
0.
0B
0$
0"
