uart/bench.v
`default_nettype none
`timescale 1 ns/1 ns

//==============================================================================

module simple_message
(
  input  logic      _clock,
  input  logic      _reset,

  output logic[7:0] _out,
  output logic      _out_valid,
  input  logic      _out_ready
);

  localparam delay_max = 20;

  logic[7:0] text[0:5];
  logic[7:0] delay, delay_;
  logic[7:0] cursor, cursor_;

  initial begin
    $readmemh("ping.hex", text);
    delay  = delay_max;
    cursor = 0;
  end

  always_comb begin
    if (_reset) begin
      delay_  = delay_max;
      cursor_ = 0;
    end else if (delay) begin
      delay_  = delay - 1;
      cursor_ = cursor;
    end else if (_out_valid && _out_ready) begin
      delay_  = cursor == 5 ? delay_max - 1 : delay;
      cursor_ = cursor == 5 ? 0 : cursor + 1;
    end else begin
      delay_  = delay;
      cursor_ = cursor;
    end
  end

  always @(posedge _clock) begin
    delay  <= delay_;
    cursor <= cursor_;
  end

  assign _out       = _reset ? 0 : delay ? 0 : text[cursor];
  assign _out_valid = _reset ? 0 : (delay == 0);

endmodule

//==============================================================================

module simple_tx
#(
  parameter clocks_per_bit
)
(
  input logic      _clock,
  input logic      _reset,

  input logic[7:0] _in,
  input logic      _in_valid,
  output logic     _in_ready,

  output logic     _out
);

  localparam bits_per_byte = 10; // 1 start + 8 data + 1 stop
  localparam delay_mid = clocks_per_bit / 2;
  localparam delay_max = clocks_per_bit - 1;
  localparam count_max = bits_per_byte - 1; // 1 start + 8 data + 9 stop to make sure we're really stopped :D

  logic[7:0] tx_delay_, tx_delay = delay_max;
  logic[7:0] tx_count_, tx_count = count_max;
  logic[9:0] tx_shift_, tx_shift = 10'b1111111111;


  always_comb begin
    _out = tx_shift[0];
    _in_ready = 0;
    tx_delay_ = tx_delay;
    tx_count_ = tx_count;
    tx_shift_ = tx_shift;

    if (_reset) begin
      tx_delay_ = delay_max;
      tx_count_ = count_max;
      tx_shift_ = 10'b1111111111;
    end else begin
      if (tx_delay < delay_max) begin
        tx_delay_ = tx_delay + 1;
      end else if (tx_count < count_max) begin
        tx_delay_ = 0;
        tx_count_ = tx_count + 1;
        tx_shift_ = { 1'b1, tx_shift[9:1] };
      end else begin
        _in_ready = 1;
        if (_in_valid) begin
          tx_delay_ = 0;
          tx_count_ = 0;
          tx_shift_ = { 1'b1, _in, 1'b0 };
        end
      end
    end
  end

  always @(posedge _clock) begin
    tx_delay <= tx_delay_;
    tx_count <= tx_count_;
    tx_shift <= tx_shift_;
  end

endmodule

//==============================================================================

module simple_rx
#(
  parameter clocks_per_bit
)
(
  input logic       _clock,
  input logic       _reset,

  input logic       _in,

  output logic[7:0] _out,
  output logic      _out_valid,
  input  logic      _out_ready
);

  localparam bits_per_byte = 10; // 1 start + 8 data + 1 stop
  localparam delay_mid = clocks_per_bit / 2;
  localparam delay_max = clocks_per_bit - 1;
  localparam count_max = bits_per_byte - 1; // 1 start + 8 data + 9 stop to make sure we're really stopped :D

  logic[7:0] delay_, delay = delay_max;
  logic[7:0] count_, count = count_max;
  logic[7:0] shift_, shift = 0;

  //----------------------------------------

  /*
  if delay < delay_max
    @delay = delay + 1
  else if count < count_max
    @delay = 0
    @count = count + 1
  else if ser_in == 0
    @delay = 0
    @count = 0

  if delay == delay_mid
    @shift = (ser_in :: shift) >> 1
    valid = count == 8
  */

  always_comb begin
    delay_ = delay;
    count_ = count;
    shift_ = shift;
    _out = 0;
    _out_valid = 0;

    if (_reset) begin
      delay_ = delay_max;
      count_ = count_max;
      shift_ = 0;
    end else begin
      if (delay < delay_max) begin
        delay_ = delay + 1;
      end else if (count < count_max) begin
        delay_ = 0;
        count_ = count + 1;
      end else if (_in == 0) begin
        delay_ = 0;
        count_ = 0;
      end

      if (delay_ == delay_mid) begin
        shift_ = {_in, shift[7:1]};
        if (count_ == count_max - 1) begin
          _out       = shift_;
          _out_valid = 1;
        end
      end
    end
  end

  //----------------------------------------

  always @(posedge _clock) begin
    delay <= delay_;
    count <= count_;
    shift <= shift_;
  end

  wire _rx_bit = delay == delay_mid && count > 0 && count < count_max;

endmodule

//==============================================================================

module byte_sink
(
  input logic      _clock,
  input logic      _reset,

  input logic[7:0] _data,
  input logic      _data_valid,
  output logic     _data_ready
);

  logic[7:0] data = 0;

  always_comb begin
    _data_ready = !_reset;
  end

  always @(posedge _clock) begin
    if (_data_valid) begin
      data <= _data;
    end
  end

endmodule

//==============================================================================

module bench();

  logic clock = 1;
  logic reset = 1;

  always #5 clock = ~clock;

  initial begin
    $dumpfile ("bench.vcd");
    $dumpvars;

    #95;
    reset = 0;

    #8000 $finish();
  end

  //----------------------------------------------------------------------------

  localparam clocks_per_bit = 1;

  simple_message msg(
    ._clock     (clock),
    ._reset     (reset),
    ._out_ready (tx._in_ready)
  );

  simple_tx #(.clocks_per_bit(clocks_per_bit)) tx(
    ._clock    (clock),
    ._reset    (reset),
    ._in       (msg._out),
    ._in_valid (msg._out_valid)
  );

  simple_rx #(.clocks_per_bit(clocks_per_bit)) rx(
    ._clock     (clock),
    ._reset     (reset),
    ._in        (tx._out),
    ._out_ready (sink._data_ready)
  );

  byte_sink sink(
    ._clock      (clock),
    ._reset      (reset),
    ._data       (rx._out),
    ._data_valid (rx._out_valid)
  );

  //----------------------------------------------------------------------------

endmodule

//==============================================================================

uart/bench.vcd
$date
	Wed Jul 31 02:21:26 2024
$end
$version
	Icarus Verilog
$end
$timescale
	1ns
$end
$scope module bench $end
$var parameter 32 ! clocks_per_bit $end
$var reg 1 " clock $end
$var reg 1 # reset $end
$scope module msg $end
$var wire 1 " _clock $end
$var wire 1 # _reset $end
$var wire 1 $ _out_valid $end
$var wire 1 % _out_ready $end
$var wire 8 & _out [7:0] $end
$var parameter 32 ' delay_max $end
$var reg 8 ( cursor [7:0] $end
$var reg 8 ) cursor_ [7:0] $end
$var reg 8 * delay [7:0] $end
$var reg 8 + delay_ [7:0] $end
$upscope $end
$scope module rx $end
$var wire 1 " _clock $end
$var wire 1 # _reset $end
$var wire 1 , _rx_bit $end
$var wire 1 - _out_ready $end
$var wire 1 . _in $end
$var parameter 32 / bits_per_byte $end
$var parameter 32 0 clocks_per_bit $end
$var parameter 33 1 count_max $end
$var parameter 33 2 delay_max $end
$var parameter 32 3 delay_mid $end
$var reg 8 4 _out [7:0] $end
$var reg 1 5 _out_valid $end
$var reg 8 6 count [7:0] $end
$var reg 8 7 count_ [7:0] $end
$var reg 8 8 delay [7:0] $end
$var reg 8 9 delay_ [7:0] $end
$var reg 8 : shift [7:0] $end
$var reg 8 ; shift_ [7:0] $end
$upscope $end
$scope module sink $end
$var wire 1 " _clock $end
$var wire 8 < _data [7:0] $end
$var wire 1 5 _data_valid $end
$var wire 1 # _reset $end
$var reg 1 - _data_ready $end
$var reg 8 = data [7:0] $end
$upscope $end
$scope module tx $end
$var wire 1 " _clock $end
$var wire 8 > _in [7:0] $end
$var wire 1 $ _in_valid $end
$var wire 1 # _reset $end
$var parameter 32 ? bits_per_byte $end
$var parameter 32 @ clocks_per_bit $end
$var parameter 33 A count_max $end
$var parameter 33 B delay_max $end
$var parameter 32 C delay_mid $end
$var reg 1 % _in_ready $end
$var reg 1 . _out $end
$var reg 8 D tx_count [7:0] $end
$var reg 8 E tx_count_ [7:0] $end
$var reg 8 F tx_delay [7:0] $end
$var reg 8 G tx_delay_ [7:0] $end
$var reg 10 H tx_shift [9:0] $end
$var reg 10 I tx_shift_ [9:0] $end
$upscope $end
$upscope $end
$enddefinitions $end
$comment Show the parameter values. $end
$dumpall
b0 C
b0 B
b1001 A
b1 @
b1010 ?
b0 3
b0 2
b1001 1
b1 0
b1010 /
b10100 '
b1 !
$end
#0
$dumpvars
b1111111111 I
b1111111111 H
b0 G
b0 F
b1001 E
b1001 D
b0 >
b0 =
b0 <
b0 ;
b0 :
b0 9
b0 8
b1001 7
b1001 6
05
b0 4
1.
0-
0,
b10100 +
b10100 *
b0 )
b0 (
b0 &
0%
0$
1#
1"
$end
#5
0"
#10
1"
#15
0"
#20
1"
#25
0"
#30
1"
#35
0"
#40
1"
#45
0"
#50
1"
#55
0"
#60
1"
#65
0"
#70
1"
#75
0"
#80
1"
#85
0"
#90
1"
#95
b10011 +
b10000000 ;
1-
1%
0"
0#
#100
b11000000 ;
b10010 +
b10000000 :
b10011 *
1"
#105
0"
#110
b10001 +
b11100000 ;
b10010 *
b11000000 :
1"
#115
0"
#120
b11110000 ;
b10000 +
b11100000 :
b10001 *
1"
#125
0"
#130
b1111 +
b11111000 ;
b10000 *
b11110000 :
1"
#135
0"
#140
b11111100 ;
b1110 +
b11111000 :
b1111 *
1"
#145
0"
#150
b1101 +
b11111110 ;
b1110 *
b11111100 :
1"
#155
0"
#160
b11111111 ;
b1100 +
b11111110 :
b1101 *
1"
#165
0"
#170
b1011 +
b1100 *
b11111111 :
1"
#175
0"
#180
b1010 +
b1011 *
1"
#185
0"
#190
b1001 +
b1010 *
1"
#195
0"
#200
b1000 +
b1001 *
1"
#205
0"
#210
b111 +
b1000 *
1"
#215
0"
#220
b110 +
b111 *
1"
#225
0"
#230
b101 +
b110 *
1"
#235
0"
#240
b100 +
b101 *
1"
#245
0"
#250
b11 +
b100 *
1"
#255
0"
#260
b10 +
b11 *
1"
#265
0"
#270
b1 +
b10 *
1"
#275
0"
#280
b0 +
b1 *
1"
#285
0"
#290
b1 )
b1010100000 I
b0 E
1%
b1010000 &
b1010000 >
1$
b0 *
1"
#295
0"
#300
b1111111 ;
b0 7
b1101001 &
b1101001 >
b1101010000 I
b1 E
0%
0.
b1 )
b1010100000 H
b0 D
b1 (
1"
#305
0"
#310
0,
b1110101000 I
b10 E
b111111 ;
b1 7
b1101010000 H
b1 D
b1111111 :
b0 6
1"
#315
0"
#320
1,
b11111 ;
b10 7
b1111010100 I
b11 E
b111111 :
b1 6
b1110101000 H
b10 D
1"
#325
0"
#330
b1111101010 I
b100 E
b1111 ;
b11 7
b1111010100 H
b11 D
b11111 :
b10 6
1"
#335
0"
#340
b111 ;
b100 7
b1111110101 I
b101 E
b1111 :
b11 6
b1111101010 H
b100 D
1"
#345
0"
#350
b1111111010 I
b110 E
1.
b10000011 ;
b101 7
b1111110101 H
b101 D
b111 :
b100 6
1"
#355
0"
#360
b1000001 ;
b110 7
b1111111101 I
b111 E
0.
b10000011 :
b101 6
b1111111010 H
b110 D
1"
#365
0"
#370
b1111111110 I
b1000 E
1.
b10100000 ;
b111 7
b1111111101 H
b111 D
b1000001 :
b110 6
1"
#375
0"
#380
15
b1010000 4
b1010000 <
b1010000 ;
b1000 7
b1111111111 I
b1001 E
0.
b10100000 :
b111 6
b1111111110 H
b1000 D
1"
#385
0"
#390
b10 )
b1011010010 I
b0 E
1%
1.
b10101000 ;
b1001 7
05
b0 4
b0 <
b1111111111 H
b1001 D
b1010000 :
b1000 6
b1010000 =
1"
#395
0"
#400
0,
b1101110 &
b1101110 >
b1010100 ;
b0 7
b1101101001 I
b1 E
0%
0.
b10 )
b10101000 :
b1001 6
b1011010010 H
b0 D
b10 (
1"
#405
0"
#410
0,
b1110110100 I
b10 E
1.
b10101010 ;
b1 7
b1101101001 H
b1 D
b1010100 :
b0 6
1"
#415
0"
#420
1,
b1010101 ;
b10 7
b1111011010 I
b11 E
0.
b10101010 :
b1 6
b1110110100 H
b10 D
1"
#425
0"
#430
b1111101101 I
b100 E
b101010 ;
b11 7
b1111011010 H
b11 D
b1010101 :
b10 6
1"
#435
0"
#440
b10010101 ;
b100 7
b1111110110 I
b101 E
1.
b101010 :
b11 6
b1111101101 H
b100 D
1"
#445
0"
#450
b1111111011 I
b110 E
0.
b1001010 ;
b101 7
b1111110110 H
b101 D
b10010101 :
b100 6
1"
#455
0"
#460
b10100101 ;
b110 7
b1111111101 I
b111 E
1.
b1001010 :
b101 6
b1111111011 H
b110 D
1"
#465
0"
#470
b1111111110 I
b1000 E
b11010010 ;
b111 7
b1111111101 H
b111 D
b10100101 :
b110 6
1"
#475
0"
#480
15
b1101001 4
b1101001 <
b1101001 ;
b1000 7
b1111111111 I
b1001 E
0.
b11010010 :
b111 6
b1111111110 H
b1000 D
1"
#485
0"
#490
b11 )
b1011011100 I
b0 E
1%
1.
b10110100 ;
b1001 7
05
b0 4
b0 <
b1111111111 H
b1001 D
b1101001 :
b1000 6
b1101001 =
1"
#495
0"
#500
0,
b1100111 &
b1100111 >
b1011010 ;
b0 7
b1101101110 I
b1 E
0%
0.
b11 )
b10110100 :
b1001 6
b1011011100 H
b0 D
b11 (
1"
#505
0"
#510
0,
b1110110111 I
b10 E
b101101 ;
b1 7
b1101101110 H
b1 D
b1011010 :
b0 6
1"
#515
0"
#520
1,
b10010110 ;
b10 7
b1111011011 I
b11 E
1.
b101101 :
b1 6
b1110110111 H
b10 D
1"
#525
0"
#530
b1111101101 I
b100 E
b11001011 ;
b11 7
b1111011011 H
b11 D
b10010110 :
b10 6
1"
#535
0"
#540
b11100101 ;
b100 7
b1111110110 I
b101 E
b11001011 :
b11 6
b1111101101 H
b100 D
1"
#545
0"
#550
b1111111011 I
b110 E
0.
b1110010 ;
b101 7
b1111110110 H
b101 D
b11100101 :
b100 6
1"
#555
0"
#560
b10111001 ;
b110 7
b1111111101 I
b111 E
1.
b1110010 :
b101 6
b1111111011 H
b110 D
1"
#565
0"
#570
b1111111110 I
b1000 E
b11011100 ;
b111 7
b1111111101 H
b111 D
b10111001 :
b110 6
1"
#575
0"
#580
15
b1101110 4
b1101110 <
b1101110 ;
b1000 7
b1111111111 I
b1001 E
0.
b11011100 :
b111 6
b1111111110 H
b1000 D
1"
#585
0"
#590
b100 )
b1011001110 I
b0 E
1%
1.
b10110111 ;
b1001 7
05
b0 4
b0 <
b1111111111 H
b1001 D
b1101110 :
b1000 6
b1101110 =
1"
#595
0"
#600
0,
b100001 &
b100001 >
b1011011 ;
b0 7
b1101100111 I
b1 E
0%
0.
b100 )
b10110111 :
b1001 6
b1011001110 H
b0 D
b100 (
1"
#605
0"
#610
0,
b1110110011 I
b10 E
1.
b10101101 ;
b1 7
b1101100111 H
b1 D
b1011011 :
b0 6
1"
#615
0"
#620
1,
b11010110 ;
b10 7
b1111011001 I
b11 E
b10101101 :
b1 6
b1110110011 H
b10 D
1"
#625
0"
#630
b1111101100 I
b100 E
b11101011 ;
b11 7
b1111011001 H
b11 D
b11010110 :
b10 6
1"
#635
0"
#640
b1110101 ;
b100 7
b1111110110 I
b101 E
0.
b11101011 :
b11 6
b1111101100 H
b100 D
1"
#645
0"
#650
b1111111011 I
b110 E
b111010 ;
b101 7
b1111110110 H
b101 D
b1110101 :
b100 6
1"
#655
0"
#660
b10011101 ;
b110 7
b1111111101 I
b111 E
1.
b111010 :
b101 6
b1111111011 H
b110 D
1"
#665
0"
#670
b1111111110 I
b1000 E
b11001110 ;
b111 7
b1111111101 H
b111 D
b10011101 :
b110 6
1"
#675
0"
#680
15
b1100111 4
b1100111 <
b1100111 ;
b1000 7
b1111111111 I
b1001 E
0.
b11001110 :
b111 6
b1111111110 H
b1000 D
1"
#685
0"
#690
b101 )
b1001000010 I
b0 E
1%
1.
b10110011 ;
b1001 7
05
b0 4
b0 <
b1111111111 H
b1001 D
b1100111 :
b1000 6
b1100111 =
1"
#695
0"
#700
0,
b1010 &
b1010 >
b1011001 ;
b0 7
b1100100001 I
b1 E
0%
0.
b101 )
b0 +
b10110011 :
b1001 6
b1001000010 H
b0 D
b101 (
1"
#705
0"
#710
0,
b1110010000 I
b10 E
1.
b10101100 ;
b1 7
b1100100001 H
b1 D
b1011001 :
b0 6
1"
#715
0"
#720
1,
b1010110 ;
b10 7
b1111001000 I
b11 E
0.
b10101100 :
b1 6
b1110010000 H
b10 D
1"
#725
0"
#730
b1111100100 I
b100 E
b101011 ;
b11 7
b1111001000 H
b11 D
b1010110 :
b10 6
1"
#735
0"
#740
b10101 ;
b100 7
b1111110010 I
b101 E
b101011 :
b11 6
b1111100100 H
b100 D
1"
#745
0"
#750
b1111111001 I
b110 E
b1010 ;
b101 7
b1111110010 H
b101 D
b10101 :
b100 6
1"
#755
0"
#760
b10000101 ;
b110 7
b1111111100 I
b111 E
1.
b1010 :
b101 6
b1111111001 H
b110 D
1"
#765
0"
#770
b1111111110 I
b1000 E
0.
b1000010 ;
b111 7
b1111111100 H
b111 D
b10000101 :
b110 6
1"
#775
0"
#780
15
b100001 4
b100001 <
b100001 ;
b1000 7
b1111111111 I
b1001 E
b1000010 :
b111 6
b1111111110 H
b1000 D
1"
#785
0"
#790
b0 )
b10011 +
b1000010100 I
b0 E
1%
1.
b10010000 ;
b1001 7
05
b0 4
b0 <
b1111111111 H
b1001 D
b100001 :
b1000 6
b100001 =
1"
#795
0"
#800
0,
b0 &
b0 >
0$
b1001000 ;
b0 7
b1100001010 I
b1 E
0%
0.
b10010 +
b10010000 :
b1001 6
b1000010100 H
b0 D
b0 (
b10011 *
1"
#805
0"
#810
0,
b10001 +
b1110000101 I
b10 E
b100100 ;
b1 7
b10010 *
b1100001010 H
b1 D
b1001000 :
b0 6
1"
#815
0"
#820
1,
b10010010 ;
b10 7
b1111000010 I
b11 E
1.
b10000 +
b100100 :
b1 6
b1110000101 H
b10 D
b10001 *
1"
#825
0"
#830
b1111 +
b1111100001 I
b100 E
0.
b1001001 ;
b11 7
b10000 *
b1111000010 H
b11 D
b10010010 :
b10 6
1"
#835
0"
#840
b10100100 ;
b100 7
b1111110000 I
b101 E
1.
b1110 +
b1001001 :
b11 6
b1111100001 H
b100 D
b1111 *
1"
#845
0"
#850
b1101 +
b1111111000 I
b110 E
0.
b1010010 ;
b101 7
b1110 *
b1111110000 H
b101 D
b10100100 :
b100 6
1"
#855
0"
#860
b101001 ;
b110 7
b1111111100 I
b111 E
b1100 +
b1010010 :
b101 6
b1111111000 H
b110 D
b1101 *
1"
#865
0"
#870
b1011 +
b1111111110 I
b1000 E
b10100 ;
b111 7
b1100 *
b1111111100 H
b111 D
b101001 :
b110 6
1"
#875
0"
#880
15
b1010 4
b1010 <
b1010 ;
b1000 7
b1111111111 I
b1001 E
b1010 +
b10100 :
b111 6
b1111111110 H
b1000 D
b1011 *
1"
#885
0"
#890
b1001 +
1%
1.
b10000101 ;
b1001 7
05
b0 4
b0 <
b1010 *
b1111111111 H
b1001 D
b1010 :
b1000 6
b1010 =
1"
#895
0"
#900
0,
b11000010 ;
b1000 +
b10000101 :
b1001 6
b1001 *
1"
#905
0"
#910
b111 +
b11100001 ;
b1000 *
b11000010 :
1"
#915
0"
#920
b11110000 ;
b110 +
b11100001 :
b111 *
1"
#925
0"
#930
b101 +
b11111000 ;
b110 *
b11110000 :
1"
#935
0"
#940
b11111100 ;
b100 +
b11111000 :
b101 *
1"
#945
0"
#950
b11 +
b11111110 ;
b100 *
b11111100 :
1"
#955
0"
#960
b11111111 ;
b10 +
b11111110 :
b11 *
1"
#965
0"
#970
b1 +
b10 *
b11111111 :
1"
#975
0"
#980
b0 +
b1 *
1"
#985
0"
#990
b1 )
b1010100000 I
b0 E
1%
b1010000 &
b1010000 >
1$
b0 *
1"
#995
0"
#1000
b1111111 ;
b0 7
b1101001 &
b1101001 >
b1101010000 I
b1 E
0%
0.
b1 )
b1010100000 H
b0 D
b1 (
1"
#1005
0"
#1010
0,
b1110101000 I
b10 E
b111111 ;
b1 7
b1101010000 H
b1 D
b1111111 :
b0 6
1"
#1015
0"
#1020
1,
b11111 ;
b10 7
b1111010100 I
b11 E
b111111 :
b1 6
b1110101000 H
b10 D
1"
#1025
0"
#1030
b1111101010 I
b100 E
b1111 ;
b11 7
b1111010100 H
b11 D
b11111 :
b10 6
1"
#1035
0"
#1040
b111 ;
b100 7
b1111110101 I
b101 E
b1111 :
b11 6
b1111101010 H
b100 D
1"
#1045
0"
#1050
b1111111010 I
b110 E
1.
b10000011 ;
b101 7
b1111110101 H
b101 D
b111 :
b100 6
1"
#1055
0"
#1060
b1000001 ;
b110 7
b1111111101 I
b111 E
0.
b10000011 :
b101 6
b1111111010 H
b110 D
1"
#1065
0"
#1070
b1111111110 I
b1000 E
1.
b10100000 ;
b111 7
b1111111101 H
b111 D
b1000001 :
b110 6
1"
#1075
0"
#1080
15
b1010000 4
b1010000 <
b1010000 ;
b1000 7
b1111111111 I
b1001 E
0.
b10100000 :
b111 6
b1111111110 H
b1000 D
1"
#1085
0"
#1090
b10 )
b1011010010 I
b0 E
1%
1.
b10101000 ;
b1001 7
05
b0 4
b0 <
b1111111111 H
b1001 D
b1010000 :
b1000 6
b1010000 =
1"
#1095
0"
#1100
0,
b1101110 &
b1101110 >
b1010100 ;
b0 7
b1101101001 I
b1 E
0%
0.
b10 )
b10101000 :
b1001 6
b1011010010 H
b0 D
b10 (
1"
#1105
0"
#1110
0,
b1110110100 I
b10 E
1.
b10101010 ;
b1 7
b1101101001 H
b1 D
b1010100 :
b0 6
1"
#1115
0"
#1120
1,
b1010101 ;
b10 7
b1111011010 I
b11 E
0.
b10101010 :
b1 6
b1110110100 H
b10 D
1"
#1125
0"
#1130
b1111101101 I
b100 E
b101010 ;
b11 7
b1111011010 H
b11 D
b1010101 :
b10 6
1"
#1135
0"
#1140
b10010101 ;
b100 7
b1111110110 I
b101 E
1.
b101010 :
b11 6
b1111101101 H
b100 D
1"
#1145
0"
#1150
b1111111011 I
b110 E
0.
b1001010 ;
b101 7
b1111110110 H
b101 D
b10010101 :
b100 6
1"
#1155
0"
#1160
b10100101 ;
b110 7
b1111111101 I
b111 E
1.
b1001010 :
b101 6
b1111111011 H
b110 D
1"
#1165
0"
#1170
b1111111110 I
b1000 E
b11010010 ;
b111 7
b1111111101 H
b111 D
b10100101 :
b110 6
1"
#1175
0"
#1180
15
b1101001 4
b1101001 <
b1101001 ;
b1000 7
b1111111111 I
b1001 E
0.
b11010010 :
b111 6
b1111111110 H
b1000 D
1"
#1185
0"
#1190
b11 )
b1011011100 I
b0 E
1%
1.
b10110100 ;
b1001 7
05
b0 4
b0 <
b1111111111 H
b1001 D
b1101001 :
b1000 6
b1101001 =
1"
#1195
0"
#1200
0,
b1100111 &
b1100111 >
b1011010 ;
b0 7
b1101101110 I
b1 E
0%
0.
b11 )
b10110100 :
b1001 6
b1011011100 H
b0 D
b11 (
1"
#1205
0"
#1210
0,
b1110110111 I
b10 E
b101101 ;
b1 7
b1101101110 H
b1 D
b1011010 :
b0 6
1"
#1215
0"
#1220
1,
b10010110 ;
b10 7
b1111011011 I
b11 E
1.
b101101 :
b1 6
b1110110111 H
b10 D
1"
#1225
0"
#1230
b1111101101 I
b100 E
b11001011 ;
b11 7
b1111011011 H
b11 D
b10010110 :
b10 6
1"
#1235
0"
#1240
b11100101 ;
b100 7
b1111110110 I
b101 E
b11001011 :
b11 6
b1111101101 H
b100 D
1"
#1245
0"
#1250
b1111111011 I
b110 E
0.
b1110010 ;
b101 7
b1111110110 H
b101 D
b11100101 :
b100 6
1"
#1255
0"
#1260
b10111001 ;
b110 7
b1111111101 I
b111 E
1.
b1110010 :
b101 6
b1111111011 H
b110 D
1"
#1265
0"
#1270
b1111111110 I
b1000 E
b11011100 ;
b111 7
b1111111101 H
b111 D
b10111001 :
b110 6
1"
#1275
0"
#1280
15
b1101110 4
b1101110 <
b1101110 ;
b1000 7
b1111111111 I
b1001 E
0.
b11011100 :
b111 6
b1111111110 H
b1000 D
1"
#1285
0"
#1290
b100 )
b1011001110 I
b0 E
1%
1.
b10110111 ;
b1001 7
05
b0 4
b0 <
b1111111111 H
b1001 D
b1101110 :
b1000 6
b1101110 =
1"
#1295
0"
#1300
0,
b100001 &
b100001 >
b1011011 ;
b0 7
b1101100111 I
b1 E
0%
0.
b100 )
b10110111 :
b1001 6
b1011001110 H
b0 D
b100 (
1"
#1305
0"
#1310
0,
b1110110011 I
b10 E
1.
b10101101 ;
b1 7
b1101100111 H
b1 D
b1011011 :
b0 6
1"
#1315
0"
#1320
1,
b11010110 ;
b10 7
b1111011001 I
b11 E
b10101101 :
b1 6
b1110110011 H
b10 D
1"
#1325
0"
#1330
b1111101100 I
b100 E
b11101011 ;
b11 7
b1111011001 H
b11 D
b11010110 :
b10 6
1"
#1335
0"
#1340
b1110101 ;
b100 7
b1111110110 I
b101 E
0.
b11101011 :
b11 6
b1111101100 H
b100 D
1"
#1345
0"
#1350
b1111111011 I
b110 E
b111010 ;
b101 7
b1111110110 H
b101 D
b1110101 :
b100 6
1"
#1355
0"
#1360
b10011101 ;
b110 7
b1111111101 I
b111 E
1.
b111010 :
b101 6
b1111111011 H
b110 D
1"
#1365
0"
#1370
b1111111110 I
b1000 E
b11001110 ;
b111 7
b1111111101 H
b111 D
b10011101 :
b110 6
1"
#1375
0"
#1380
15
b1100111 4
b1100111 <
b1100111 ;
b1000 7
b1111111111 I
b1001 E
0.
b11001110 :
b111 6
b1111111110 H
b1000 D
1"
#1385
0"
#1390
b101 )
b1001000010 I
b0 E
1%
1.
b10110011 ;
b1001 7
05
b0 4
b0 <
b1111111111 H
b1001 D
b1100111 :
b1000 6
b1100111 =
1"
#1395
0"
#1400
0,
b1010 &
b1010 >
b1011001 ;
b0 7
b1100100001 I
b1 E
0%
0.
b101 )
b0 +
b10110011 :
b1001 6
b1001000010 H
b0 D
b101 (
1"
#1405
0"
#1410
0,
b1110010000 I
b10 E
1.
b10101100 ;
b1 7
b1100100001 H
b1 D
b1011001 :
b0 6
1"
#1415
0"
#1420
1,
b1010110 ;
b10 7
b1111001000 I
b11 E
0.
b10101100 :
b1 6
b1110010000 H
b10 D
1"
#1425
0"
#1430
b1111100100 I
b100 E
b101011 ;
b11 7
b1111001000 H
b11 D
b1010110 :
b10 6
1"
#1435
0"
#1440
b10101 ;
b100 7
b1111110010 I
b101 E
b101011 :
b11 6
b1111100100 H
b100 D
1"
#1445
0"
#1450
b1111111001 I
b110 E
b1010 ;
b101 7
b1111110010 H
b101 D
b10101 :
b100 6
1"
#1455
0"
#1460
b10000101 ;
b110 7
b1111111100 I
b111 E
1.
b1010 :
b101 6
b1111111001 H
b110 D
1"
#1465
0"
#1470
b1111111110 I
b1000 E
0.
b1000010 ;
b111 7
b1111111100 H
b111 D
b10000101 :
b110 6
1"
#1475
0"
#1480
15
b100001 4
b100001 <
b100001 ;
b1000 7
b1111111111 I
b1001 E
b1000010 :
b111 6
b1111111110 H
b1000 D
1"
#1485
0"
#1490
b0 )
b10011 +
b1000010100 I
b0 E
1%
1.
b10010000 ;
b1001 7
05
b0 4
b0 <
b1111111111 H
b1001 D
b100001 :
b1000 6
b100001 =
1"
#1495
0"
#1500
0,
b0 &
b0 >
0$
b1001000 ;
b0 7
b1100001010 I
b1 E
0%
0.
b10010 +
b10010000 :
b1001 6
b1000010100 H
b0 D
b0 (
b10011 *
1"
#1505
0"
#1510
0,
b10001 +
b1110000101 I
b10 E
b100100 ;
b1 7
b10010 *
b1100001010 H
b1 D
b1001000 :
b0 6
1"
#1515
0"
#1520
1,
b10010010 ;
b10 7
b1111000010 I
b11 E
1.
b10000 +
b100100 :
b1 6
b1110000101 H
b10 D
b10001 *
1"
#1525
0"
#1530
b1111 +
b1111100001 I
b100 E
0.
b1001001 ;
b11 7
b10000 *
b1111000010 H
b11 D
b10010010 :
b10 6
1"
#1535
0"
#1540
b10100100 ;
b100 7
b1111110000 I
b101 E
1.
b1110 +
b1001001 :
b11 6
b1111100001 H
b100 D
b1111 *
1"
#1545
0"
#1550
b1101 +
b1111111000 I
b110 E
0.
b1010010 ;
b101 7
b1110 *
b1111110000 H
b101 D
b10100100 :
b100 6
1"
#1555
0"
#1560
b101001 ;
b110 7
b1111111100 I
b111 E
b1100 +
b1010010 :
b101 6
b1111111000 H
b110 D
b1101 *
1"
#1565
0"
#1570
b1011 +
b1111111110 I
b1000 E
b10100 ;
b111 7
b1100 *
b1111111100 H
b111 D
b101001 :
b110 6
1"
#1575
0"
#1580
15
b1010 4
b1010 <
b1010 ;
b1000 7
b1111111111 I
b1001 E
b1010 +
b10100 :
b111 6
b1111111110 H
b1000 D
b1011 *
1"
#1585
0"
#1590
b1001 +
1%
1.
b10000101 ;
b1001 7
05
b0 4
b0 <
b1010 *
b1111111111 H
b1001 D
b1010 :
b1000 6
b1010 =
1"
#1595
0"
#1600
0,
b11000010 ;
b1000 +
b10000101 :
b1001 6
b1001 *
1"
#1605
0"
#1610
b111 +
b11100001 ;
b1000 *
b11000010 :
1"
#1615
0"
#1620
b11110000 ;
b110 +
b11100001 :
b111 *
1"
#1625
0"
#1630
b101 +
b11111000 ;
b110 *
b11110000 :
1"
#1635
0"
#1640
b11111100 ;
b100 +
b11111000 :
b101 *
1"
#1645
0"
#1650
b11 +
b11111110 ;
b100 *
b11111100 :
1"
#1655
0"
#1660
b11111111 ;
b10 +
b11111110 :
b11 *
1"
#1665
0"
#1670
b1 +
b10 *
b11111111 :
1"
#1675
0"
#1680
b0 +
b1 *
1"
#1685
0"
#1690
b1 )
b1010100000 I
b0 E
1%
b1010000 &
b1010000 >
1$
b0 *
1"
#1695
0"
#1700
b1111111 ;
b0 7
b1101001 &
b1101001 >
b1101010000 I
b1 E
0%
0.
b1 )
b1010100000 H
b0 D
b1 (
1"
#1705
0"
#1710
0,
b1110101000 I
b10 E
b111111 ;
b1 7
b1101010000 H
b1 D
b1111111 :
b0 6
1"
#1715
0"
#1720
1,
b11111 ;
b10 7
b1111010100 I
b11 E
b111111 :
b1 6
b1110101000 H
b10 D
1"
#1725
0"
#1730
b1111101010 I
b100 E
b1111 ;
b11 7
b1111010100 H
b11 D
b11111 :
b10 6
1"
#1735
0"
#1740
b111 ;
b100 7
b1111110101 I
b101 E
b1111 :
b11 6
b1111101010 H
b100 D
1"
#1745
0"
#1750
b1111111010 I
b110 E
1.
b10000011 ;
b101 7
b1111110101 H
b101 D
b111 :
b100 6
1"
#1755
0"
