block_ram/bram.sv
//------------------------------------------------------------------------------

module bram_512x8
(
  input  logic      clock,
  input  logic[8:0] raddr,
  input  logic[8:0] waddr,
  input  logic[7:0] wdata,
  input  logic      wren,
  output logic[7:0] out
);

  always @(posedge clock) begin
    if (wren) begin
      data[waddr] <= wdata;
    end
    out <= waddr == raddr && wren ? wdata : data[raddr];
  end

  logic[7:0] data[0:511];

endmodule

//------------------------------------------------------------------------------

module bram_unaligned
(
  input  logic       clock,
  input  logic[10:0] raddr,
  input  logic[10:0] waddr,
  input  logic[31:0] wdata,
  input  logic       wren,
  output logic[31:0] out
);

  always @* begin

    case (raddr[1:0])
    2'b00: begin raddr0 = (raddr >> 2) + 0; raddr1 = (raddr >> 2) + 0; raddr2 = (raddr >> 2) + 0; raddr3 = (raddr >> 2) + 0; end
    2'b01: begin raddr0 = (raddr >> 2) + 1; raddr1 = (raddr >> 2) + 0; raddr2 = (raddr >> 2) + 0; raddr3 = (raddr >> 2) + 0; end
    2'b10: begin raddr0 = (raddr >> 2) + 1; raddr1 = (raddr >> 2) + 1; raddr2 = (raddr >> 2) + 0; raddr3 = (raddr >> 2) + 0; end
    2'b11: begin raddr0 = (raddr >> 2) + 1; raddr1 = (raddr >> 2) + 1; raddr2 = (raddr >> 2) + 1; raddr3 = (raddr >> 2) + 0; end
    endcase

    case (waddr[1:0])
    2'b00: begin waddr0 = (waddr >> 2) + 0; waddr1 = (waddr >> 2) + 0; waddr2 = (waddr >> 2) + 0; waddr3 = (waddr >> 2) + 0; end
    2'b01: begin waddr0 = (waddr >> 2) + 1; waddr1 = (waddr >> 2) + 0; waddr2 = (waddr >> 2) + 0; waddr3 = (waddr >> 2) + 0; end
    2'b10: begin waddr0 = (waddr >> 2) + 1; waddr1 = (waddr >> 2) + 1; waddr2 = (waddr >> 2) + 0; waddr3 = (waddr >> 2) + 0; end
    2'b11: begin waddr0 = (waddr >> 2) + 1; waddr1 = (waddr >> 2) + 1; waddr2 = (waddr >> 2) + 1; waddr3 = (waddr >> 2) + 0; end
    endcase

    case (waddr[1:0])
    2'b00: begin wdata0 = wdata[7:0]; wdata1 = wdata[15:8]; wdata2 = wdata[23:16]; wdata3 = wdata[31:24]; end
    2'b01: begin wdata1 = wdata[7:0]; wdata2 = wdata[15:8]; wdata3 = wdata[23:16]; wdata0 = wdata[31:24]; end
    2'b10: begin wdata2 = wdata[7:0]; wdata3 = wdata[15:8]; wdata0 = wdata[23:16]; wdata1 = wdata[31:24]; end
    2'b11: begin wdata3 = wdata[7:0]; wdata0 = wdata[15:8]; wdata1 = wdata[23:16]; wdata2 = wdata[31:24]; end
    endcase

    wren0 = wren;
    wren1 = wren;
    wren2 = wren;
    wren3 = wren;

    case (raddr[1:0])
    2'b00: begin out[ 7: 0] = out0; out[15: 8] = out1; out[23:16] = out2; out[31:24] = out3; end
    2'b01: begin out[ 7: 0] = out1; out[15: 8] = out2; out[23:16] = out3; out[31:24] = out0; end
    2'b10: begin out[ 7: 0] = out2; out[15: 8] = out3; out[23:16] = out0; out[31:24] = out1; end
    2'b11: begin out[ 7: 0] = out3; out[15: 8] = out0; out[23:16] = out1; out[31:24] = out2; end
    endcase
  end

  logic[8:0] raddr0;
  logic[8:0] waddr0;
  logic[7:0] wdata0;
  logic      wren0;
  logic[7:0] out0;
  bram_512x8 ram0(.clock(clock), .raddr(raddr0), .waddr(waddr0), .wdata(wdata0), .wren(wren0), .out(out0));

  logic[8:0] raddr1;
  logic[8:0] waddr1;
  logic[7:0] wdata1;
  logic      wren1;
  logic[7:0] out1;
  bram_512x8 ram1(.clock(clock), .raddr(raddr1), .waddr(waddr1), .wdata(wdata1), .wren(wren1), .out(out1));

  logic[8:0] raddr2;
  logic[8:0] waddr2;
  logic[7:0] wdata2;
  logic      wren2;
  logic[7:0] out2;
  bram_512x8 ram2(.clock(clock), .raddr(raddr2), .waddr(waddr2), .wdata(wdata2), .wren(wren2), .out(out2));

  logic[8:0] raddr3;
  logic[8:0] waddr3;
  logic[7:0] wdata3;
  logic      wren3;
  logic[7:0] out3;
  bram_512x8 ram3(.clock(clock), .raddr(raddr3), .waddr(waddr3), .wdata(wdata3), .wren(wren3), .out(out3));


endmodule

//------------------------------------------------------------------------------

block_ram/bram_testbench.sv
`include "bram.sv"
`timescale 1ns/100ps

module bram_testbench();

  always #5 clock = ~clock;

  initial begin
    $display("Hello World\n");

    clock = 0;
    raddr = 0;
    waddr = 0;
    wdata = 0;
    wren  = 0;
    #1

    raddr = 0;
    waddr = 0;
    wdata = 32'h00000000;
    wren  = 1;
    #10 $display("%x", out);

    raddr = 4;
    waddr = 4;
    wdata = 32'h00000000;
    wren  = 1;
    #10 $display("%x", out);

    raddr = 3;
    waddr = 3;
    wdata = 32'h12345678;
    wren  = 1;
    #10 $display("%x", out);

    $display();


    raddr = 4;
    wren = 0;
    #10 $write("%x", out);

    raddr = 0;
    wren = 0;
    #10 $write("%x", out);

    $display();
    $finish();
  end

  logic       clock;
  logic[10:0] raddr;
  logic[10:0] waddr;
  logic[31:0] wdata;
  logic       wren;
  logic[31:0] out;
  bram_unaligned dut(.clock(clock), .raddr(raddr), .waddr(waddr), .wdata(wdata), .wren(wren), .out(out));

  initial begin
    $dumpfile("dump.vcd");
    $dumpvars(0, bram_testbench);
  end

endmodule

block_ram/dump.vcd
$date
	Mon Nov 13 22:13:07 2023
$end
$version
	Icarus Verilog
$end
$timescale
	100ps
$end
$scope module bram_testbench $end
$var wire 32 ! out [31:0] $end
$var reg 1 " clock $end
$var reg 11 # raddr [10:0] $end
$var reg 11 $ waddr [10:0] $end
$var reg 32 % wdata [31:0] $end
$var reg 1 & wren $end
$scope module dut $end
$var wire 1 " clock $end
$var wire 11 ' raddr [10:0] $end
$var wire 11 ( waddr [10:0] $end
$var wire 32 ) wdata [31:0] $end
$var wire 1 & wren $end
$var wire 8 * out3 [7:0] $end
$var wire 8 + out2 [7:0] $end
$var wire 8 , out1 [7:0] $end
$var wire 8 - out0 [7:0] $end
$var reg 32 . out [31:0] $end
$var reg 9 / raddr0 [8:0] $end
$var reg 9 0 raddr1 [8:0] $end
$var reg 9 1 raddr2 [8:0] $end
$var reg 9 2 raddr3 [8:0] $end
$var reg 9 3 waddr0 [8:0] $end
$var reg 9 4 waddr1 [8:0] $end
$var reg 9 5 waddr2 [8:0] $end
$var reg 9 6 waddr3 [8:0] $end
$var reg 8 7 wdata0 [7:0] $end
$var reg 8 8 wdata1 [7:0] $end
$var reg 8 9 wdata2 [7:0] $end
$var reg 8 : wdata3 [7:0] $end
$var reg 1 ; wren0 $end
$var reg 1 < wren1 $end
$var reg 1 = wren2 $end
$var reg 1 > wren3 $end
$scope module ram0 $end
$var wire 1 " clock $end
$var wire 9 ? raddr [8:0] $end
$var wire 9 @ waddr [8:0] $end
$var wire 8 A wdata [7:0] $end
$var wire 1 ; wren $end
$var reg 8 B out [7:0] $end
$upscope $end
$scope module ram1 $end
$var wire 1 " clock $end
$var wire 9 C raddr [8:0] $end
$var wire 9 D waddr [8:0] $end
$var wire 8 E wdata [7:0] $end
$var wire 1 < wren $end
$var reg 8 F out [7:0] $end
$upscope $end
$scope module ram2 $end
$var wire 1 " clock $end
$var wire 9 G raddr [8:0] $end
$var wire 9 H waddr [8:0] $end
$var wire 8 I wdata [7:0] $end
$var wire 1 = wren $end
$var reg 8 J out [7:0] $end
$upscope $end
$scope module ram3 $end
$var wire 1 " clock $end
$var wire 9 K raddr [8:0] $end
$var wire 9 L waddr [8:0] $end
$var wire 8 M wdata [7:0] $end
$var wire 1 > wren $end
$var reg 8 N out [7:0] $end
$upscope $end
$upscope $end
$upscope $end
$enddefinitions $end
$comment Show the parameter values. $end
$dumpall
$end
#0
$dumpvars
bx N
b0 M
b0 L
b0 K
bx J
b0 I
b0 H
b0 G
bx F
b0 E
b0 D
b0 C
bx B
b0 A
b0 @
b0 ?
0>
0=
0<
0;
b0 :
b0 9
b0 8
b0 7
b0 6
b0 5
b0 4
b0 3
b0 2
b0 1
b0 0
b0 /
bx .
bx -
bx ,
bx +
bx *
b0 )
b0 (
b0 '
0&
b0 %
b0 $
b0 #
0"
bx !
$end
#10
1>
1=
1<
1;
1&
#50
b0 !
b0 .
b0 -
b0 B
b0 ,
b0 F
b0 +
b0 J
b0 *
b0 N
1"
#100
0"
#110
b1 6
b1 L
b1 5
b1 H
b1 4
b1 D
b1 3
b1 @
b1 2
b1 K
b1 1
b1 G
b1 0
b1 C
b1 /
b1 ?
b100 $
b100 (
b100 #
b100 '
#150
1"
#200
0"
#210
b10010 9
b10010 I
b110100 8
b110100 E
b1010110 7
b1010110 A
b1111000 :
b1111000 M
b0 6
b0 L
b0 2
b0 K
b10010001101000101011001111000 %
b10010001101000101011001111000 )
b11 $
b11 (
b11 #
b11 '
#250
b10010001101000101011001111000 !
b10010001101000101011001111000 .
b1010110 -
b1010110 B
b110100 ,
b110100 F
b10010 +
b10010 J
b1111000 *
b1111000 N
1"
#300
0"
#310
b1111000000100100011010001010110 !
b1111000000100100011010001010110 .
0>
0=
0<
0;
b1 2
b1 K
0&
b100 #
b100 '
#350
b100100011010001010110 !
b100100011010001010110 .
b0 *
b0 N
1"
#400
0"
#410
b0 2
b0 K
b0 1
b0 G
b0 0
b0 C
b0 /
b0 ?
b0 #
b0 '
#450
b1111000000000000000000000000000 !
b1111000000000000000000000000000 .
b0 -
b0 B
b0 ,
b0 F
b0 +
b0 J
b1111000 *
b1111000 N
1"
