block_ram/bram.sv
//------------------------------------------------------------------------------

module bram_512x8
(
  input  logic      clock,
  input  logic[8:0] raddr,
  input  logic[8:0] waddr,
  input  logic[7:0] wdata,
  input  logic      wren,
  output logic[7:0] out
);

  always @(posedge clock) begin
    if (wren) begin
      data[waddr] <= wdata;
    end
    out <= waddr == raddr && wren ? wdata : data[raddr];
  end

  logic[7:0] data[0:511];

endmodule

//------------------------------------------------------------------------------

module bram_256x16
(
  input  logic       clock,
  input  logic[7:0]  raddr,
  input  logic[7:0]  waddr,
  input  logic[15:0] wdata,
  input  logic       wren,
  output logic[15:0] out
);

  always @(posedge clock) begin
    if (wren) begin
      data[waddr] <= wdata;
    end
    out <= waddr == raddr && wren ? wdata : data[raddr];
  end

  logic[15:0] data[0:255];

endmodule

//------------------------------------------------------------------------------

module bram_align1_2048
(
  input  logic       clock,
  input  logic[10:0] raddr,
  input  logic[10:0] waddr,
  input  logic[31:0] wdata,
  input  logic[2:0]  wsize,
  input  logic       wren,
  output logic[31:0] out
);

  always @* begin

    case (raddr[1:0])
    2'b00: begin raddr0 = (raddr >> 2) + 0; raddr1 = (raddr >> 2) + 0; raddr2 = (raddr >> 2) + 0; raddr3 = (raddr >> 2) + 0; end
    2'b01: begin raddr0 = (raddr >> 2) + 1; raddr1 = (raddr >> 2) + 0; raddr2 = (raddr >> 2) + 0; raddr3 = (raddr >> 2) + 0; end
    2'b10: begin raddr0 = (raddr >> 2) + 1; raddr1 = (raddr >> 2) + 1; raddr2 = (raddr >> 2) + 0; raddr3 = (raddr >> 2) + 0; end
    2'b11: begin raddr0 = (raddr >> 2) + 1; raddr1 = (raddr >> 2) + 1; raddr2 = (raddr >> 2) + 1; raddr3 = (raddr >> 2) + 0; end
    endcase

    case (waddr[1:0])
    2'b00: begin waddr0 = (waddr >> 2) + 0; waddr1 = (waddr >> 2) + 0; waddr2 = (waddr >> 2) + 0; waddr3 = (waddr >> 2) + 0; end
    2'b01: begin waddr0 = (waddr >> 2) + 1; waddr1 = (waddr >> 2) + 0; waddr2 = (waddr >> 2) + 0; waddr3 = (waddr >> 2) + 0; end
    2'b10: begin waddr0 = (waddr >> 2) + 1; waddr1 = (waddr >> 2) + 1; waddr2 = (waddr >> 2) + 0; waddr3 = (waddr >> 2) + 0; end
    2'b11: begin waddr0 = (waddr >> 2) + 1; waddr1 = (waddr >> 2) + 1; waddr2 = (waddr >> 2) + 1; waddr3 = (waddr >> 2) + 0; end
    endcase

    case (waddr[1:0])
    2'b00: begin wdata0 = wdata[7:0]; wdata1 = wdata[15:8]; wdata2 = wdata[23:16]; wdata3 = wdata[31:24]; end
    2'b01: begin wdata1 = wdata[7:0]; wdata2 = wdata[15:8]; wdata3 = wdata[23:16]; wdata0 = wdata[31:24]; end
    2'b10: begin wdata2 = wdata[7:0]; wdata3 = wdata[15:8]; wdata0 = wdata[23:16]; wdata1 = wdata[31:24]; end
    2'b11: begin wdata3 = wdata[7:0]; wdata0 = wdata[15:8]; wdata1 = wdata[23:16]; wdata2 = wdata[31:24]; end
    endcase

    case (raddr[1:0])
    2'b00: begin out[ 7: 0] = out0; out[15: 8] = out1; out[23:16] = out2; out[31:24] = out3; end
    2'b01: begin out[ 7: 0] = out1; out[15: 8] = out2; out[23:16] = out3; out[31:24] = out0; end
    2'b10: begin out[ 7: 0] = out2; out[15: 8] = out3; out[23:16] = out0; out[31:24] = out1; end
    2'b11: begin out[ 7: 0] = out3; out[15: 8] = out0; out[23:16] = out1; out[31:24] = out2; end
    endcase
  end

  logic[8:0] raddr0;
  logic[8:0] waddr0;
  logic[7:0] wdata0;
  logic[7:0] out0;
  bram_512x8 ram0(.clock(clock), .raddr(raddr0), .waddr(waddr0), .wdata(wdata0), .wren(wren), .out(out0));

  logic[8:0] raddr1;
  logic[8:0] waddr1;
  logic[7:0] wdata1;
  logic[7:0] out1;
  bram_512x8 ram1(.clock(clock), .raddr(raddr1), .waddr(waddr1), .wdata(wdata1), .wren(wren), .out(out1));

  logic[8:0] raddr2;
  logic[8:0] waddr2;
  logic[7:0] wdata2;
  logic[7:0] out2;
  bram_512x8 ram2(.clock(clock), .raddr(raddr2), .waddr(waddr2), .wdata(wdata2), .wren(wren), .out(out2));

  logic[8:0] raddr3;
  logic[8:0] waddr3;
  logic[7:0] wdata3;
  logic[7:0] out3;
  bram_512x8 ram3(.clock(clock), .raddr(raddr3), .waddr(waddr3), .wdata(wdata3), .wren(wren), .out(out3));


endmodule

//------------------------------------------------------------------------------

module bram_align2_1024
(
  input  logic       clock,
  input  logic[9:0]  raddr,
  input  logic[9:0]  waddr,
  input  logic[31:0] wdata,
  input  logic[2:0]  wsize,
  input  logic       wren,
  output logic[31:0] out
);

  always @* begin

    case (raddr[1])
    0: begin raddr0 = (raddr >> 2) + 0; raddr1 = (raddr >> 2) + 0; end
    1: begin raddr0 = (raddr >> 2) + 1; raddr1 = (raddr >> 2) + 0; end
    endcase

    case (waddr[1])
    0: begin waddr0 = (waddr >> 2) + 0; waddr1 = (waddr >> 2) + 0; end
    1: begin waddr0 = (waddr >> 2) + 1; waddr1 = (waddr >> 2) + 0; end
    endcase

    case (waddr[1])
    0: begin wdata0 = wdata[15: 0]; wdata1 = wdata[31:16]; end
    1: begin wdata1 = wdata[15: 0]; wdata0 = wdata[31:16]; end
    endcase

    case (raddr[1])
    0: begin out[15: 0] = out0; out[31:16] = out1; end
    1: begin out[15: 0] = out1; out[31:16] = out0; end
    endcase
  end

  logic[7:0]  raddr0;
  logic[7:0]  waddr0;
  logic[15:0] wdata0;
  logic[15:0] out0;
  bram_256x16 ram0(.clock(clock), .raddr(raddr0), .waddr(waddr0), .wdata(wdata0), .wren(wren), .out(out0));

  logic[7:0]  raddr1;
  logic[7:0]  waddr1;
  logic[15:0] wdata1;
  logic[15:0] out1;
  bram_256x16 ram1(.clock(clock), .raddr(raddr1), .waddr(waddr1), .wdata(wdata1), .wren(wren), .out(out1));

endmodule

//------------------------------------------------------------------------------

block_ram/testbench.sv
`include "bram.sv"
`timescale 1ns/100ps

module testbench();

  logic clock;
  always #5 clock = ~clock;

  task test_mem();
    int i, j, k;

    for (int j = 0; j < 16; j++) begin
      for (int i = 0; i < 4; i++) begin
        do_mem(j * 16 + i * 4, 0, 0, 0);
        $write("%02x ", out[7:0]);
        $write("%02x ", out[15:8]);
        $write("%02x ", out[23:16]);
        $write("%02x ", out[31:24]);
      end
      $write("\n");
    end
    $write("\n");
  endtask;

  task do_mem(logic[10:0] _raddr, logic[10:0] _waddr, logic[31:0] _wdata, logic _wren);
    raddr = _raddr;
    waddr = _waddr;
    wdata = _wdata;
    wren  = _wren;
    assert(0 == 0);
    #10;
  endtask

  initial begin
    int offset;
    int i, j, k;

    $dumpfile("testbench.vcd");
    $dumpvars(0, testbench);

    clock = 0;
    raddr = 0;
    waddr = 0;
    wdata = 0;
    wren  = 0;

    for (i = 0; i < 16; i++) begin
      do_mem(0, i * 17, 32'h12345678, 1);
    end

    test_mem();

    $finish();
  end

  /*
  logic[10:0] raddr;
  logic[10:0] waddr;
  logic[31:0] wdata;
  logic[2:0]  wsize;
  logic       wren;
  logic[31:0] out;
  bram_align1_2048 dut(.clock(clock), .raddr(raddr), .waddr(waddr), .wdata(wdata), .wren(wren), .out(out));
  */

  logic[9:0]  raddr;
  logic[9:0]  waddr;
  logic[31:0] wdata;
  logic[2:0]  wsize;
  logic       wren;
  logic[31:0] out;
  bram_align2_1024 dut(.clock(clock), .raddr(raddr), .waddr(waddr), .wdata(wdata), .wsize(wsize), .wren(wren), .out(out));


endmodule

block_ram/testbench.vcd
$date
	Tue Nov 14 14:09:26 2023
$end
$version
	Icarus Verilog
$end
$timescale
	100ps
$end
$scope module testbench $end
$var wire 32 ! out [31:0] $end
$var reg 1 " clock $end
$var reg 10 # raddr [9:0] $end
$var reg 10 $ waddr [9:0] $end
$var reg 32 % wdata [31:0] $end
$var reg 1 & wren $end
$var reg 3 ' wsize [2:0] $end
$scope module dut $end
$var wire 1 " clock $end
$var wire 10 ( raddr [9:0] $end
$var wire 10 ) waddr [9:0] $end
$var wire 32 * wdata [31:0] $end
$var wire 1 & wren $end
$var wire 3 + wsize [2:0] $end
$var wire 16 , out1 [15:0] $end
$var wire 16 - out0 [15:0] $end
$var reg 32 . out [31:0] $end
$var reg 8 / raddr0 [7:0] $end
$var reg 8 0 raddr1 [7:0] $end
$var reg 8 1 waddr0 [7:0] $end
$var reg 8 2 waddr1 [7:0] $end
$var reg 16 3 wdata0 [15:0] $end
$var reg 16 4 wdata1 [15:0] $end
$scope module ram0 $end
$var wire 1 " clock $end
$var wire 8 5 raddr [7:0] $end
$var wire 8 6 waddr [7:0] $end
$var wire 16 7 wdata [15:0] $end
$var wire 1 & wren $end
$var reg 16 8 out [15:0] $end
$upscope $end
$scope module ram1 $end
$var wire 1 " clock $end
$var wire 8 9 raddr [7:0] $end
$var wire 8 : waddr [7:0] $end
$var wire 16 ; wdata [15:0] $end
$var wire 1 & wren $end
$var reg 16 < out [15:0] $end
$upscope $end
$upscope $end
$scope begin $unm_blk_33 $end
$var integer 32 = i [31:0] $end
$upscope $end
$scope task do_mem $end
$var reg 11 > _raddr [10:0] $end
$var reg 11 ? _waddr [10:0] $end
$var reg 32 @ _wdata [31:0] $end
$var reg 1 A _wren $end
$upscope $end
$scope task test_mem $end
$scope begin $ivl_for_loop0 $end
$var integer 32 B j [31:0] $end
$scope begin $ivl_for_loop1 $end
$var integer 32 C i [31:0] $end
$upscope $end
$upscope $end
$upscope $end
$upscope $end
$enddefinitions $end
$comment Show the parameter values. $end
$dumpall
$end
#0
$dumpvars
b0 C
b0 B
1A
b10010001101000101011001111000 @
b0 ?
b0 >
b0 =
bx <
b1001000110100 ;
b0 :
b0 9
bx 8
b101011001111000 7
b0 6
b0 5
b1001000110100 4
b101011001111000 3
b0 2
b0 1
b0 0
b0 /
bx .
bx -
bx ,
bx +
b10010001101000101011001111000 *
b0 )
b0 (
bx '
1&
b10010001101000101011001111000 %
b0 $
b0 #
0"
bx !
$end
#50
b10010001101000101011001111000 !
b10010001101000101011001111000 .
b101011001111000 -
b101011001111000 8
b1001000110100 ,
b1001000110100 <
1"
#100
b100 2
b100 :
b100 1
b100 6
0"
b10001 $
b10001 )
b10001 ?
b1 =
#150
1"
#200
b1001000110100 3
b1001000110100 7
b101011001111000 4
b101011001111000 ;
b1000 2
b1000 :
b1001 1
b1001 6
0"
b100010 $
b100010 )
b100010 ?
b10 =
#250
1"
#300
b1100 2
b1100 :
b1101 1
b1101 6
0"
b110011 $
b110011 )
b110011 ?
b11 =
#350
1"
#400
b1001000110100 4
b1001000110100 ;
b101011001111000 3
b101011001111000 7
b10001 2
b10001 :
b10001 1
b10001 6
0"
b1000100 $
b1000100 )
b1000100 ?
b100 =
#450
1"
#500
b10101 2
b10101 :
b10101 1
b10101 6
0"
b1010101 $
b1010101 )
b1010101 ?
b101 =
#550
1"
#600
b1001000110100 3
b1001000110100 7
b101011001111000 4
b101011001111000 ;
b11001 2
b11001 :
b11010 1
b11010 6
0"
b1100110 $
b1100110 )
b1100110 ?
b110 =
#650
1"
#700
b11101 2
b11101 :
b11110 1
b11110 6
0"
b1110111 $
b1110111 )
b1110111 ?
b111 =
#750
1"
#800
b1001000110100 4
b1001000110100 ;
b101011001111000 3
b101011001111000 7
b100010 2
b100010 :
b100010 1
b100010 6
0"
b10001000 $
b10001000 )
b10001000 ?
b1000 =
#850
1"
#900
b100110 2
b100110 :
b100110 1
b100110 6
0"
b10011001 $
b10011001 )
b10011001 ?
b1001 =
#950
1"
#1000
b1001000110100 3
b1001000110100 7
b101011001111000 4
b101011001111000 ;
b101010 2
b101010 :
b101011 1
b101011 6
0"
b10101010 $
b10101010 )
b10101010 ?
b1010 =
#1050
1"
#1100
b101110 2
b101110 :
b101111 1
b101111 6
0"
b10111011 $
b10111011 )
b10111011 ?
b1011 =
#1150
1"
#1200
b1001000110100 4
b1001000110100 ;
b101011001111000 3
b101011001111000 7
b110011 2
b110011 :
b110011 1
b110011 6
0"
b11001100 $
b11001100 )
b11001100 ?
b1100 =
#1250
1"
#1300
b110111 2
b110111 :
b110111 1
b110111 6
0"
b11011101 $
b11011101 )
b11011101 ?
b1101 =
#1350
1"
#1400
b1001000110100 3
b1001000110100 7
b101011001111000 4
b101011001111000 ;
b111011 2
b111011 :
b111100 1
b111100 6
0"
b11101110 $
b11101110 )
b11101110 ?
b1110 =
#1450
1"
#1500
b111111 2
b111111 :
b1000000 1
b1000000 6
0"
b11111111 $
b11111111 )
b11111111 ?
b1111 =
#1550
1"
#1600
b0 4
b0 ;
b0 3
b0 7
b0 2
b0 :
b0 1
b0 6
0"
0&
b0 %
b0 *
b0 $
b0 )
0A
b0 @
b0 ?
b10000 =
#1650
1"
#1700
b1 0
b1 9
b1 /
b1 5
0"
b100 #
b100 (
b100 >
b1 C
#1750
bx !
bx .
bx ,
bx <
bx -
bx 8
1"
#1800
b10 0
b10 9
b10 /
b10 5
0"
b1000 #
b1000 (
b1000 >
b10 C
#1850
1"
#1900
b11 0
b11 9
b11 /
b11 5
0"
b1100 #
b1100 (
b1100 >
b11 C
#1950
1"
#2000
b100 0
b100 9
b100 /
b100 5
0"
b10000 #
b10000 (
b10000 >
b1 B
b0 C
#2050
b10010001101000101011001111000 !
b10010001101000101011001111000 .
b101011001111000 -
b101011001111000 8
b1001000110100 ,
b1001000110100 <
1"
#2100
b101 0
b101 9
b101 /
b101 5
0"
b10100 #
b10100 (
b10100 >
b1 C
#2150
bx !
bx .
bx ,
bx <
bx -
bx 8
1"
#2200
b110 0
b110 9
b110 /
b110 5
0"
b11000 #
b11000 (
b11000 >
b10 C
#2250
1"
#2300
b111 0
b111 9
b111 /
b111 5
0"
b11100 #
b11100 (
b11100 >
b11 C
#2350
1"
#2400
b1000 0
b1000 9
b1000 /
b1000 5
0"
b100000 #
b100000 (
b100000 >
b10 B
b0 C
#2450
b101011001111000xxxxxxxxxxxxxxxx !
b101011001111000xxxxxxxxxxxxxxxx .
b101011001111000 ,
b101011001111000 <
1"
#2500
b1001 0
b1001 9
b1001 /
b1001 5
0"
b100100 #
b100100 (
b100100 >
b1 C
#2550
bx0001001000110100 !
bx0001001000110100 .
bx ,
bx <
b1001000110100 -
b1001000110100 8
1"
#2600
b1010 0
b1010 9
b1010 /
b1010 5
0"
b101000 #
b101000 (
b101000 >
b10 C
#2650
bx !
bx .
bx -
bx 8
1"
#2700
b1011 0
b1011 9
b1011 /
b1011 5
0"
b101100 #
b101100 (
b101100 >
b11 C
#2750
1"
#2800
b1100 0
b1100 9
b1100 /
b1100 5
0"
b110000 #
b110000 (
b110000 >
b11 B
b0 C
#2850
b101011001111000xxxxxxxxxxxxxxxx !
b101011001111000xxxxxxxxxxxxxxxx .
b101011001111000 ,
b101011001111000 <
1"
#2900
b1101 0
b1101 9
b1101 /
b1101 5
0"
b110100 #
b110100 (
b110100 >
b1 C
#2950
bx0001001000110100 !
bx0001001000110100 .
bx ,
bx <
b1001000110100 -
b1001000110100 8
1"
#3000
b1110 0
b1110 9
b1110 /
b1110 5
0"
b111000 #
b111000 (
b111000 >
b10 C
#3050
bx !
bx .
bx -
bx 8
1"
#3100
b1111 0
b1111 9
b1111 /
b1111 5
0"
b111100 #
b111100 (
b111100 >
b11 C
#3150
1"
#3200
b10000 0
b10000 9
b10000 /
b10000 5
0"
b1000000 #
b1000000 (
b1000000 >
b100 B
b0 C
#3250
1"
#3300
b10001 0
b10001 9
b10001 /
b10001 5
0"
b1000100 #
b1000100 (
b1000100 >
b1 C
#3350
b10010001101000101011001111000 !
b10010001101000101011001111000 .
b1001000110100 ,
b1001000110100 <
b101011001111000 -
b101011001111000 8
1"
#3400
b10010 0
b10010 9
b10010 /
b10010 5
0"
b1001000 #
b1001000 (
b1001000 >
b10 C
#3450
bx !
bx .
bx -
bx 8
bx ,
bx <
1"
#3500
b10011 0
b10011 9
b10011 /
b10011 5
0"
b1001100 #
b1001100 (
b1001100 >
b11 C
#3550
1"
#3600
b10100 0
b10100 9
b10100 /
b10100 5
0"
b1010000 #
b1010000 (
b1010000 >
b101 B
b0 C
#3650
1"
#3700
b10101 0
b10101 9
b10101 /
b10101 5
0"
b1010100 #
b1010100 (
b1010100 >
b1 C
#3750
b10010001101000101011001111000 !
b10010001101000101011001111000 .
b1001000110100 ,
b1001000110100 <
b101011001111000 -
b101011001111000 8
1"
#3800
b10110 0
b10110 9
b10110 /
b10110 5
0"
b1011000 #
b1011000 (
b1011000 >
b10 C
#3850
bx !
bx .
bx -
bx 8
bx ,
bx <
1"
#3900
b10111 0
b10111 9
b10111 /
b10111 5
0"
b1011100 #
b1011100 (
b1011100 >
b11 C
#3950
1"
#4000
b11000 0
b11000 9
b11000 /
b11000 5
0"
b1100000 #
b1100000 (
b1100000 >
b110 B
b0 C
#4050
1"
#4100
b11001 0
b11001 9
b11001 /
b11001 5
0"
b1100100 #
b1100100 (
b1100100 >
b1 C
#4150
b101011001111000xxxxxxxxxxxxxxxx !
b101011001111000xxxxxxxxxxxxxxxx .
b101011001111000 ,
b101011001111000 <
1"
#4200
b11010 0
b11010 9
b11010 /
b11010 5
0"
b1101000 #
b1101000 (
b1101000 >
b10 C
#4250
bx0001001000110100 !
bx0001001000110100 .
b1001000110100 -
b1001000110100 8
bx ,
bx <
1"
#4300
b11011 0
b11011 9
b11011 /
b11011 5
0"
b1101100 #
b1101100 (
b1101100 >
b11 C
#4350
bx !
bx .
bx -
bx 8
1"
#4400
b11100 0
b11100 9
b11100 /
b11100 5
0"
b1110000 #
b1110000 (
b1110000 >
b111 B
b0 C
#4450
1"
#4500
b11101 0
b11101 9
b11101 /
b11101 5
0"
b1110100 #
b1110100 (
b1110100 >
b1 C
#4550
b101011001111000xxxxxxxxxxxxxxxx !
b101011001111000xxxxxxxxxxxxxxxx .
b101011001111000 ,
b101011001111000 <
1"
#4600
b11110 0
b11110 9
b11110 /
b11110 5
0"
b1111000 #
b1111000 (
b1111000 >
b10 C
#4650
bx0001001000110100 !
bx0001001000110100 .
b1001000110100 -
b1001000110100 8
bx ,
bx <
1"
#4700
b11111 0
b11111 9
b11111 /
b11111 5
0"
b1111100 #
b1111100 (
b1111100 >
b11 C
#4750
bx !
bx .
bx -
bx 8
1"
#4800
b100000 0
b100000 9
b100000 /
b100000 5
0"
b10000000 #
b10000000 (
b10000000 >
b1000 B
b0 C
#4850
1"
#4900
b100001 0
b100001 9
b100001 /
b100001 5
0"
b10000100 #
b10000100 (
b10000100 >
b1 C
#4950
1"
#5000
b100010 0
b100010 9
b100010 /
b100010 5
0"
b10001000 #
b10001000 (
b10001000 >
b10 C
#5050
b10010001101000101011001111000 !
b10010001101000101011001111000 .
b101011001111000 -
b101011001111000 8
b1001000110100 ,
b1001000110100 <
1"
#5100
b100011 0
b100011 9
b100011 /
b100011 5
0"
b10001100 #
b10001100 (
b10001100 >
b11 C
#5150
bx !
bx .
bx ,
bx <
bx -
bx 8
1"
#5200
b100100 0
b100100 9
b100100 /
b100100 5
0"
b10010000 #
b10010000 (
b10010000 >
b1001 B
b0 C
#5250
1"
#5300
b100101 0
b100101 9
b100101 /
b100101 5
0"
b10010100 #
b10010100 (
b10010100 >
b1 C
#5350
1"
#5400
b100110 0
b100110 9
b100110 /
b100110 5
0"
b10011000 #
b10011000 (
b10011000 >
b10 C
#5450
b10010001101000101011001111000 !
b10010001101000101011001111000 .
b101011001111000 -
b101011001111000 8
b1001000110100 ,
b1001000110100 <
1"
#5500
b100111 0
b100111 9
b100111 /
b100111 5
0"
b10011100 #
b10011100 (
b10011100 >
b11 C
#5550
bx !
bx .
bx ,
bx <
bx -
bx 8
1"
#5600
b101000 0
b101000 9
b101000 /
b101000 5
0"
b10100000 #
b10100000 (
b10100000 >
b1010 B
b0 C
#5650
1"
#5700
b101001 0
b101001 9
b101001 /
b101001 5
0"
b10100100 #
b10100100 (
b10100100 >
b1 C
#5750
1"
#5800
b101010 0
b101010 9
b101010 /
b101010 5
0"
b10101000 #
b10101000 (
b10101000 >
b10 C
#5850
b101011001111000xxxxxxxxxxxxxxxx !
b101011001111000xxxxxxxxxxxxxxxx .
b101011001111000 ,
b101011001111000 <
1"
#5900
b101011 0
b101011 9
b101011 /
b101011 5
0"
b10101100 #
b10101100 (
b10101100 >
b11 C
#5950
bx0001001000110100 !
bx0001001000110100 .
bx ,
bx <
b1001000110100 -
b1001000110100 8
1"
#6000
b101100 0
b101100 9
b101100 /
b101100 5
0"
b10110000 #
b10110000 (
b10110000 >
b1011 B
b0 C
#6050
bx !
bx .
bx -
bx 8
1"
#6100
b101101 0
b101101 9
b101101 /
b101101 5
0"
b10110100 #
b10110100 (
b10110100 >
b1 C
#6150
1"
#6200
b101110 0
b101110 9
b101110 /
b101110 5
0"
b10111000 #
b10111000 (
b10111000 >
b10 C
#6250
b101011001111000xxxxxxxxxxxxxxxx !
b101011001111000xxxxxxxxxxxxxxxx .
b101011001111000 ,
b101011001111000 <
1"
#6300
b101111 0
b101111 9
b101111 /
b101111 5
0"
b10111100 #
b10111100 (
b10111100 >
b11 C
#6350
bx0001001000110100 !
bx0001001000110100 .
bx ,
bx <
b1001000110100 -
b1001000110100 8
1"
#6400
b110000 0
b110000 9
b110000 /
b110000 5
0"
b11000000 #
b11000000 (
b11000000 >
b1100 B
b0 C
#6450
bx !
bx .
bx -
bx 8
1"
#6500
b110001 0
b110001 9
b110001 /
b110001 5
0"
b11000100 #
b11000100 (
b11000100 >
b1 C
#6550
1"
#6600
b110010 0
b110010 9
b110010 /
b110010 5
0"
b11001000 #
b11001000 (
b11001000 >
b10 C
#6650
1"
#6700
b110011 0
b110011 9
b110011 /
b110011 5
0"
b11001100 #
b11001100 (
b11001100 >
b11 C
#6750
b10010001101000101011001111000 !
b10010001101000101011001111000 .
b1001000110100 ,
b1001000110100 <
b101011001111000 -
b101011001111000 8
1"
#6800
b110100 0
b110100 9
b110100 /
b110100 5
0"
b11010000 #
b11010000 (
b11010000 >
b1101 B
b0 C
#6850
bx !
bx .
bx -
bx 8
bx ,
bx <
1"
#6900
b110101 0
b110101 9
b110101 /
b110101 5
0"
b11010100 #
b11010100 (
b11010100 >
b1 C
#6950
1"
#7000
b110110 0
b110110 9
b110110 /
b110110 5
0"
b11011000 #
b11011000 (
b11011000 >
b10 C
#7050
1"
#7100
b110111 0
b110111 9
b110111 /
b110111 5
0"
b11011100 #
b11011100 (
b11011100 >
b11 C
#7150
b10010001101000101011001111000 !
b10010001101000101011001111000 .
b1001000110100 ,
b1001000110100 <
b101011001111000 -
b101011001111000 8
1"
#7200
b111000 0
b111000 9
b111000 /
b111000 5
0"
b11100000 #
b11100000 (
b11100000 >
b1110 B
b0 C
#7250
bx !
bx .
bx -
bx 8
bx ,
bx <
1"
#7300
b111001 0
b111001 9
b111001 /
b111001 5
0"
b11100100 #
b11100100 (
b11100100 >
b1 C
#7350
1"
#7400
b111010 0
b111010 9
b111010 /
b111010 5
0"
b11101000 #
b11101000 (
b11101000 >
b10 C
#7450
1"
#7500
b111011 0
b111011 9
b111011 /
b111011 5
0"
b11101100 #
b11101100 (
b11101100 >
b11 C
#7550
b101011001111000xxxxxxxxxxxxxxxx !
b101011001111000xxxxxxxxxxxxxxxx .
b101011001111000 ,
b101011001111000 <
1"
#7600
b111100 0
b111100 9
b111100 /
b111100 5
0"
b11110000 #
b11110000 (
b11110000 >
b1111 B
b0 C
#7650
bx0001001000110100 !
bx0001001000110100 .
b1001000110100 -
b1001000110100 8
bx ,
bx <
1"
#7700
b111101 0
b111101 9
b111101 /
b111101 5
0"
b11110100 #
b11110100 (
b11110100 >
b1 C
#7750
bx !
bx .
bx -
bx 8
1"
#7800
b111110 0
b111110 9
b111110 /
b111110 5
0"
b11111000 #
b11111000 (
b11111000 >
b10 C
#7850
1"
#7900
b111111 0
b111111 9
b111111 /
b111111 5
0"
b11111100 #
b11111100 (
b11111100 >
b11 C
#7950
b101011001111000xxxxxxxxxxxxxxxx !
b101011001111000xxxxxxxxxxxxxxxx .
b101011001111000 ,
b101011001111000 <
1"
#8000
0"
b10000 B
b100 C
